Workbook

Sheet Сводка
A1: Сухие строительные смеси — ассортимент трёх производителей (разведка 09.10.2026)
A2: Считаются товары без учёта цвета и фасовки. Источник — полный обход каталогов td-perel.ru, dauer.ru, osnovit.ru 09.10.2026 (лист «Как собрано»). Числа считаются формулами из листа «Товары».
A4: Раздел будущего сайта | B4: Perel | C4: Dauer | D4: Основит | E4: Всего | F4: У скольких производителей
A5: Цветные кладочные растворы | B5: =COUNTIFS(Товары!$A$2:$A$272,"Perel",Товары!$B$2:$B$272,$A5,Товары!$C$2:$C$272,"<>нет") | C5: =COUNTIFS(Товары!$A$2:$A$272,"Dauer",Товары!$B$2:$B$272,$A5,Товары!$C$2:$C$272,"<>нет") | D5: =COUNTIFS(Товары!$A$2:$A$272,"Основит",Товары!$B$2:$B$272,$A5,Товары!$C$2:$C$272,"<>нет") | E5: =SUM(B5:D5) | F5: =(B5>0)+(C5>0)+(D5>0)
A6: Кладочные растворы: рядовые и белые/серые | B6: =COUNTIFS(Товары!$A$2:$A$272,"Perel",Товары!$B$2:$B$272,$A6,Товары!$C$2:$C$272,"<>нет") | C6: =COUNTIFS(Товары!$A$2:$A$272,"Dauer",Товары!$B$2:$B$272,$A6,Товары!$C$2:$C$272,"<>нет") | D6: =COUNTIFS(Товары!$A$2:$A$272,"Основит",Товары!$B$2:$B$272,$A6,Товары!$C$2:$C$272,"<>нет") | E6: =SUM(B6:D6) | F6: =(B6>0)+(C6>0)+(D6>0)
A7: Тёплые (теплоизоляционные) кладочные растворы | B7: =COUNTIFS(Товары!$A$2:$A$272,"Perel",Товары!$B$2:$B$272,$A7,Товары!$C$2:$C$272,"<>нет") | C7: =COUNTIFS(Товары!$A$2:$A$272,"Dauer",Товары!$B$2:$B$272,$A7,Товары!$C$2:$C$272,"<>нет") | D7: =COUNTIFS(Товары!$A$2:$A$272,"Основит",Товары!$B$2:$B$272,$A7,Товары!$C$2:$C$272,"<>нет") | E7: =SUM(B7:D7) | F7: =(B7>0)+(C7>0)+(D7>0)
A8: Расшивка швов кирпичной кладки | B8: =COUNTIFS(Товары!$A$2:$A$272,"Perel",Товары!$B$2:$B$272,$A8,Товары!$C$2:$C$272,"<>нет") | C8: =COUNTIFS(Товары!$A$2:$A$272,"Dauer",Товары!$B$2:$B$272,$A8,Товары!$C$2:$C$272,"<>нет") | D8: =COUNTIFS(Товары!$A$2:$A$272,"Основит",Товары!$B$2:$B$272,$A8,Товары!$C$2:$C$272,"<>нет") | E8: =SUM(B8:D8) | F8: =(B8>0)+(C8>0)+(D8>0)
A9: Клей для блоков и газобетона | B9: =COUNTIFS(Товары!$A$2:$A$272,"Perel",Товары!$B$2:$B$272,$A9,Товары!$C$2:$C$272,"<>нет") | C9: =COUNTIFS(Товары!$A$2:$A$272,"Dauer",Товары!$B$2:$B$272,$A9,Товары!$C$2:$C$272,"<>нет") | D9: =COUNTIFS(Товары!$A$2:$A$272,"Основит",Товары!$B$2:$B$272,$A9,Товары!$C$2:$C$272,"<>нет") | E9: =SUM(B9:D9) | F9: =(B9>0)+(C9>0)+(D9>0)
A10: Гипсовый монтажный клей (ГКЛ, ПГП) | B10: =COUNTIFS(Товары!$A$2:$A$272,"Perel",Товары!$B$2:$B$272,$A10,Товары!$C$2:$C$272,"<>нет") | C10: =COUNTIFS(Товары!$A$2:$A$272,"Dauer",Товары!$B$2:$B$272,$A10,Товары!$C$2:$C$272,"<>нет") | D10: =COUNTIFS(Товары!$A$2:$A$272,"Основит",Товары!$B$2:$B$272,$A10,Товары!$C$2:$C$272,"<>нет") | E10: =SUM(B10:D10) | F10: =(B10>0)+(C10>0)+(D10>0)
A11: Цементно-песчаные смеси М150–М400, пескобетон | B11: =COUNTIFS(Товары!$A$2:$A$272,"Perel",Товары!$B$2:$B$272,$A11,Товары!$C$2:$C$272,"<>нет") | C11: =COUNTIFS(Товары!$A$2:$A$272,"Dauer",Товары!$B$2:$B$272,$A11,Товары!$C$2:$C$272,"<>нет") | D11: =COUNTIFS(Товары!$A$2:$A$272,"Основит",Товары!$B$2:$B$272,$A11,Товары!$C$2:$C$272,"<>нет") | E11: =SUM(B11:D11) | F11: =(B11>0)+(C11>0)+(D11>0)
A12: Штукатурки гипсовые | B12: =COUNTIFS(Товары!$A$2:$A$272,"Perel",Товары!$B$2:$B$272,$A12,Товары!$C$2:$C$272,"<>нет") | C12: =COUNTIFS(Товары!$A$2:$A$272,"Dauer",Товары!$B$2:$B$272,$A12,Товары!$C$2:$C$272,"<>нет") | D12: =COUNTIFS(Товары!$A$2:$A$272,"Основит",Товары!$B$2:$B$272,$A12,Товары!$C$2:$C$272,"<>нет") | E12: =SUM(B12:D12) | F12: =(B12>0)+(C12>0)+(D12>0)
A13: Штукатурки цементные и цементно-известковые (вкл. обрызг) | B13: =COUNTIFS(Товары!$A$2:$A$272,"Perel",Товары!$B$2:$B$272,$A13,Товары!$C$2:$C$272,"<>нет") | C13: =COUNTIFS(Товары!$A$2:$A$272,"Dauer",Товары!$B$2:$B$272,$A13,Товары!$C$2:$C$272,"<>нет") | D13: =COUNTIFS(Товары!$A$2:$A$272,"Основит",Товары!$B$2:$B$272,$A13,Товары!$C$2:$C$272,"<>нет") | E13: =SUM(B13:D13) | F13: =(B13>0)+(C13>0)+(D13>0)
A14: Шпаклёвки гипсовые | B14: =COUNTIFS(Товары!$A$2:$A$272,"Perel",Товары!$B$2:$B$272,$A14,Товары!$C$2:$C$272,"<>нет") | C14: =COUNTIFS(Товары!$A$2:$A$272,"Dauer",Товары!$B$2:$B$272,$A14,Товары!$C$2:$C$272,"<>нет") | D14: =COUNTIFS(Товары!$A$2:$A$272,"Основит",Товары!$B$2:$B$272,$A14,Товары!$C$2:$C$272,"<>нет") | E14: =SUM(B14:D14) | F14: =(B14>0)+(C14>0)+(D14>0)
A15: Шпаклёвки цементные | B15: =COUNTIFS(Товары!$A$2:$A$272,"Perel",Товары!$B$2:$B$272,$A15,Товары!$C$2:$C$272,"<>нет") | C15: =COUNTIFS(Товары!$A$2:$A$272,"Dauer",Товары!$B$2:$B$272,$A15,Товары!$C$2:$C$272,"<>нет") | D15: =COUNTIFS(Товары!$A$2:$A$272,"Основит",Товары!$B$2:$B$272,$A15,Товары!$C$2:$C$272,"<>нет") | E15: =SUM(B15:D15) | F15: =(B15>0)+(C15>0)+(D15>0)
A16: Шпаклёвки полимерные (сухие) | B16: =COUNTIFS(Товары!$A$2:$A$272,"Perel",Товары!$B$2:$B$272,$A16,Товары!$C$2:$C$272,"<>нет") | C16: =COUNTIFS(Товары!$A$2:$A$272,"Dauer",Товары!$B$2:$B$272,$A16,Товары!$C$2:$C$272,"<>нет") | D16: =COUNTIFS(Товары!$A$2:$A$272,"Основит",Товары!$B$2:$B$272,$A16,Товары!$C$2:$C$272,"<>нет") | E16: =SUM(B16:D16) | F16: =(B16>0)+(C16>0)+(D16>0)
... A27: Краска сухая (цементно-известковая) | B27: =COUNTIFS(Товары!$A$2:$A$272,"Perel",Товары!$B$2:$B$272,$A27,Товары!$C$2:$C$272,"<>нет") | C27: =COUNTIFS(Товары!$A$2:$A$272,"Dauer",Товары!$B$2:$B$272,$A27,Товары!$C$2:$C$272,"<>нет") | D27: =COUNTIFS(Товары!$A$2:$A$272,"Основит",Товары!$B$2:$B$272,$A27,Товары!$C$2:$C$272,"<>нет") | E27: =SUM(B27:D27) | F27: =(B27>0)+(C27>0)+(D27>0)
A28: Итого сухих смесей | B28: =SUM(B5:B27) | C28: =SUM(C5:C27) | D28: =SUM(D5:D27) | E28: =SUM(E5:E27)
A30: Сопутствующие не сухие товары (грунты, краски, пасты, добавки, бытовая химия) | B30: =COUNTIFS(Товары!$A$2:$A$272,"Perel",Товары!$C$2:$C$272,"нет") | C30: =COUNTIFS(Товары!$A$2:$A$272,"Dauer",Товары!$C$2:$C$272,"нет") | D30: =COUNTIFS(Товары!$A$2:$A$272,"Основит",Товары!$C$2:$C$272,"нет") | E30: =SUM(B30:D30)
A31: Разделов, где позиции есть у всех трёх | E31: =COUNTIF(F5:F27,3)
A32: Разделов, где позиции есть только у одного | E32: =COUNTIF(F5:F27,1)
A34: Цветные кладочные растворы — тема соседнего сайта «Цветные кладочные смеси»: здесь коротко и ссылкой.

Sheet Товары
A1: Производитель | B1: Раздел будущего сайта | C1: Сухая смесь | D1: Товар (без цвета и фасовки) | E1: Название на сайте производителя | F1: Карточек у производителя (цвета, фасовки) | G1: Назначение — дословно | H1: Фасовка — дословно | I1: Расход — дословно | J1: Толщина слоя или шва — дословно | K1: Норматив — дословно | L1: Зимняя версия | M1: Цвета — дословно | N1: Ссылка на карточку | O1: Примечание разбора
A2: Dauer | B2: Цветные кладочные растворы | C2: да | D2: Dauer BRICK.COLOR 250 | E2: Dauer BRICK.COLOR 250 цветная кладочная смесь армированная | F2: 1 | G2: Для монтажа и одновременной отделки швов кладочных элементов с водопоглощением от 6 до 12% | H2: 3,5 – 4,5 литра воды на мешок 25 кг или 7 – 9 литров на мешок 50 кг | J2: 5-15 мм | K2: ГОСТ Р 58272 | L2: есть | M2: 25 цветов | N2: https://dauer.ru/catalog/montazhnye-i-kladochnye/dauer-brick-color-250/ | O2: Строки «Фасовка» на карточке нет: мешки 25 и 50 кг упомянуты только в приготовлении раствора; «Смесь поставляется в бумажных мешках». Есть зимняя версия (характеристики «(зимняя версия)», нанесение -10…+30°С; PDF «+ЗИМА»). Внутренние/наружные работы не указаны. Расход раствора не указан. Список 25 цветов на карточке текстом не приведён. Минимальное оседание раствора в пустотах кирпича (особенности
A3: Dauer | B3: Цветные кладочные растворы | C3: да | D3: Dauer BRICK.COLOR 251 | E3: Dauer BRICK.COLOR 251 цветная кладочная смесь армированная | F3: 1 | G3: Для монтажа и одновременной отделки швов кладочных элементов с водопоглощением от 5 до 18% (полнотелый и пустотелый облицовочный керамический кирпич, кирпич ручной формовки, рядовой керамический и плотный силикатный кирпич, кирпичи или блоки из бетона и натурального камня). | H3: 3,5 – 4,5 литра воды на мешок 25 кг или 7 – 9 литров на мешок 50 кг | J3: 5-15 мм | K3: ГОСТ Р 58272 | L3: есть | M3: 25 цветов | N3: https://dauer.ru/catalog/montazhnye-i-kladochnye/dauer-brick-color-251/ | O3: Строки «Фасовка» нет: мешки 25 и 50 кг упомянуты только в приготовлении раствора. Есть зимняя версия (характеристики «(зимняя версия)», нанесение -10…+30°С; PDF «+ЗИМА»). Внутренние/наружные работы не указаны. Расход раствора не указан. Список 25 цветов на карточке текстом не приведён. Добавка против высолов (особенности).
A4: Dauer | B4: Цветные кладочные растворы | C4: да | D4: Dauer BRICK.COLOR 252 | E4: Dauer BRICK.COLOR 252 цветная кладочная смесь армированная | F4: 1 | G4: Для монтажа и одновременной отделки швов кладочных элементов с водопоглощением от 1 до 5% (полнотелый и пустотелый облицовочный клинкерный кирпич, блоки из бетона и натурального камня). | H4: Смесь поставляется в бумажных мешках. | J4: 5-15 мм | K4: ГОСТ Р 58272 | L4: есть | M4: 25 цветов | N4: https://dauer.ru/catalog/montazhnye-i-kladochnye/dauer-brick-color-252/ | O4: Масса мешка не указана вовсе (только «бумажные мешки»), раздела «Выполнение работ» на карточке нет. Для клинкера: марка 15 МПа, морозостойкость 150 циклов. Есть зимняя версия (характеристики «(зимняя версия)», нанесение -10…+30°С; PDF «+ЗИМА»). Внутренние/наружные работы не указаны. Расход раствора не указан. Список 25 цветов на карточке текстом не приведён.
A5: Perel | B5: Цветные кладочные растворы | C5: да | D5: Perel NL | E5: Белая кладочная смесь Perel NL 0105, 25 кг | F5: 28 | G5: Цветная смесь Perel NL 0105 для кладки облицовочного кирпича с низким водопоглощением от 0 до 5% (клинкерный кирпич и т.п.). | H5: фасовка 50 кг | K5: Нанесение смеси производить в соответствии со СП 70.13330.2012 | L5: есть | N5: https://td-perel.ru/catalog/perel-nl/belaya-kladochnaya-smes-perel-nl-25-kg/ | O5: Цветной кладочный для клинкера (пересечение с сайтом «Цветные кладочные смеси»). Артикул: в названии и описании 0105, в характеристиках 0101 — какой верный, не ясно. Общие замечания по NL — в batch_notes.
A6: Perel | B6: Цветные кладочные растворы | C6: да | D6: Perel SL | E6: Белая кладочная смесь Perel SL 0005, 25 кг | F6: 28 | G6: Цветная смесь Perel SL 0005 для кладки облицовочного кирпича с средним водопоглощением от 5 до 12 % (керамический кирпич и т.п.). | H6: фасовка 50 кг | K6: СП 70.13330.2012 | L6: есть | M6: цвет красный | N6: https://td-perel.ru/catalog/perel-sl/belaya-kladochnaya-smes-perel-sl-25-kg/ | O6: В заголовке единственной из пачки стоит артикул («SL 0005, 25 кг»). Белый внутри цветной линейки SL — тип masonry_colored. Расхода нет; толщина шва числом не указана. «Зима» упомянута в описании, отдельной карточки нет.
A7: Perel | B7: Цветные кладочные растворы | C7: да | D7: Perel VL | E7: Белая кладочная смесь Perel VL 0205, 25 кг | F7: 28 | G7: Цветная смесь Perel VL 0205 для кладки облицовочного кирпича с высоким водопоглощением от 5 до 17% (кирпич ручной формовки и т.п.). | H7: фасовка 25 кг | K7: СП 70.13330.2012 | L7: есть | M7: цвет бежевый | N7: https://td-perel.ru/catalog/perel-vl/belaya-kladochnaya-smes-perel-vl-25-kg/ | O7: белый цвет внутри цветной линейки VL (оставлен masonry_colored); артикул 0205 вынесен в заголовок; основа вяжущего и расход на кладку не указаны; модификация «зима» упоминается только в описании
A8: Основит | B8: Цветные кладочные растворы | C8: да | D8: Основит Брикформ MC11 | E8: Раствор кладочный зимний для облицовочного кирпича Основит Брикформ MC11 F 25 кг | F8: 3 | G8: Кладочный раствор ОСНОВИТ БРИКФОРМ МС11 F зимний предназначен для кладки стен из облицовочного кирпича с водопоглощением до 12% с возможностью расшивки швов в момент укладки при температуре окружающей среды и основания от -10 до + 10°С. | H8: Мешок 25кг | I8: Расход смеси, кг на 1м² кладки (ложковая кладка) 50 кг | J8: Рекомендуемая толщина шва кладки 5-15 мм | K8: G M100, ГОСТ Р 58272-2018 | L8: есть | M8: 17 цветов | N8: https://osnovit.ru/catalog/kladochnye-rastvory/kladochnyy-rastvor-osnovit-brikform-ms11-f-zimniy-belyy-010/ | O8: URL карточки «…zimniy-belyy-010», но страница описывает весь MC11 F (17 цветов); есть оговорка о фасовке в мешок «БРИКФОРМ МС11 БЕЛЫЙ 010» со стикером «зимний». Расхождение температур: в назначении «от -10 до + 10°С», в характеристиках «-10…+5 ºС». Строка «Прочность сцепления с основанием» в характеристиках повторена дважды. Документация (описание, техкарта) названа, но ссылок PDF во входе нет. Ле
A9: Основит | B9: Цветные кладочные растворы | C9: да | D9: Основит Брикформ MC11/1 | E9: Раствор кладочный зимний белый для облицовочного кирпича Основит Брикформ MC11/1 F 25 кг | F9: 3 | G9: предназначен для кладки стен и перегородок из облицовочного кирпича водопоглощением более 12% с возможностью расшивки швов в момент укладки при температуре окружающей среды и основания от -10 до + 10°С. | H9: Мешок 25кг | I9: 50 кг | J9: 5-15 мм | K9: G M100, ГОСТ Р 58272-2018 | L9: есть | M9: 34 цвета | N9: https://osnovit.ru/catalog/kladochnye-rastvory/kladochnyy-rastvor-osnovit-brikform-ms11-1-f/ | O9: Зимняя модификация линии Брикформ MC11/1 (раздел «Цветные кладочные растворы»), но в зиме только белый цвет — тип masonry_colored выбран по линейке, можно считать и masonry_ordinary. Пересекается с сайтом «Цветные кладочные смеси». Расход 50 кг на 1 м² ложковой кладки. Описание «от -10 до + 10°С», характеристики «-10…+5 ºС». Строка «Прочность сцепления с основанием» на странице повторена дважды; о
A10: Dauer | B10: Кладочные растворы: рядовые и белые/серые | C10: да | D10: Dauer BRICK.COLOR 253 | E10: Dauer BRICK.COLOR 253 кладочная смесь для рядового кирпича | F10: 1 | G10: Предназначена для монтажа забутовочных кладочных элементов (полнотелый и пустотелый керамический кирпич, натуральный камень, рядовой керамический и плотный силикатный кирпич, кирпичи из бетона). | H10: 3,25 – 3,75 литра воды на мешок 25 кг или 6,5 – 7,5 литров на мешок 50 кг | J10: 5-20 мм | K10: ГОСТ Р 58272 | L10: есть | N10: https://dauer.ru/catalog/montazhnye-i-kladochnye/dauer-brick-color-253/ | O10: Сомнение в типе: линейка BRICK.COLOR, но H1 «кладочная смесь для рядового кирпича», назначение — забутовочная кладка, цвета не указаны → masonry_ordinary. Строки «Фасовка» нет: мешки 25 и 50 кг упомянуты только в приготовлении раствора. Расход раствора не указан. Есть зимняя версия (PDF «+ЗИМА»). Внутр./наруж. не указано, но шов описан как свето-, водо- и морозостойкий.
A11: Основит | B11: Кладочные растворы: рядовые и белые/серые | C11: да | D11: Основит Рокформ MC110 | E11: Раствор кладочный для рядового кирпича Основит Рокформ MC110 25 кг | F11: 3 | G11: Кладочный раствор ОСНОВИТ РОКФОРМ МС110 предназначен для забутовки и кладки стен из облицовочного и рядового кирпича. | H11: 25 кг | I11: 400-440 кг | J11: 5-15 мм | K11: G M150, ГОСТ Р 58272-2018 | L11: есть | M11: серый | N11: https://osnovit.ru/catalog/kladochnye-rastvory-osnovit/rokform-ms110-N/ | O11: URL с суффиксом «-N», в title страницы «(25 кг) Н» — возможно, старая/дублирующая версия карточки Рокформ MC110 из другой пачки; сверить при склейке. ГОСТ/марка смеси на странице не указаны. Тип: серый кладочный для рядового и облицовочного кирпича (masonry_ordinary); можно спорить с masonry_universal_cps. Зимняя версия «Рокформ MC110 F» упоминается только в сопутствующих товарах других карточек.
A12: Dauer | B12: Тёплые (теплоизоляционные) кладочные растворы | C12: да | D12: Dauer TEFIX LM | E12: Dauer TEFIX LM Кладочный раствор для теплой керамики | F12: 1 | G12: Предназначен для возведения несущих и ограждающих конструкций из «теплой» керамики, газобетона и легкого пустотелого кирпича, а также блоков из бетона на пористых заполнителях (керамзитобетон). | H12: 20 кг. | I12: Расход раствора при слое шва 12 мм | J12: 5-20 мм | K12: ГОСТ Р 58272 | L12: есть | N12: https://dauer.ru/catalog/montazhnye-i-kladochnye/tefix-lm-kladochnyy-rastvor/ | O12: Полное наименование «Dauer Quader Tefix LM» (TEFIX — подлинейка QUADER). Содержит перлит и армирующие волокна. Расход при шве 12 мм таблицей (формат / толщина стены / на 1 м2 кладки / на 1 блок): 4,5 NF 8 см ~6 кг ~0,6 кг; 6,7 NF 12 см ~8 кг ~0,9 кг; 10,7 NF 38 см ~27 кг ~1,6 кг; 12,3 NF 44 см ~32 кг ~1,8 кг; 14,3 NF 51 см ~35 кг ~2,0 кг. Есть зимняя версия.
A13: Dauer | B13: Тёплые (теплоизоляционные) кладочные растворы | C13: да | D13: Dauer TEFIX SM | E13: Dauer TEFIX SM Кладочный раствор теплоизоляционный | F13: 1 | G13: Предназначен для возведения несущих и ограждающих стен из поризованных керамических блоков, легких блоков из ячеистого бетона (в т.ч. пено- и газобетон), а также блоков из бетона на пористых заполнителях (керамзитобетон). | H13: 25 кг. | I13: РАСХОД РАСТВОРА ПРИ СЛОЕ ШВА 12 мм | J13: 5 - 20 мм | K13: ГОСТ Р 58272 | L13: есть | N13: https://dauer.ru/catalog/montazhnye-i-kladochnye/quader-tefix-sm/ | O13: Полное наименование «Dauer Quader Tefix SM». Расхождение: фасовка 25 кг, а вода дана «на 30 кг смеси» (7,8 – 9,6л). Подвижность записана «150 + 10 мм» (у соседей «±»). Расход при шве 12 мм таблицей (на 1 м2 кладки / на 1 блок): 4,5 NF ~7 кг ~0,7 кг; 6,7 NF ~10 кг ~1,0 кг; 10,7 NF ~32 кг ~1,8 кг; 12,3 NF ~38 кг ~2,1 кг; 14,3 NF ~42 кг ~2,4 кг. Есть зимняя версия (срок годности 6 месяцев).
A14: Dauer | B14: Тёплые (теплоизоляционные) кладочные растворы | C14: да | D14: Dauer TEFIX SW | E14: Dauer TEFIX SW Кладочный раствор для теплой керамики | F14: 1 | G14: Предназначен для возведения несущих и ограждающих конструкций из «теплой» керамики, газобетона и легкого пустотелого кирпича, а также блоков из бетона на пористых заполнителях (керамзитобетон). | H14: 17,5 кг. | J14: 5-20 мм | K14: ГОСТ Р 58272 | L14: есть | N14: https://dauer.ru/catalog/montazhnye-i-kladochnye/tefix-sw/ | O14: Полное наименование «Dauer Quader Tefix SW». Фасовка 17,5 кг; «Выход до 34 л.*» — «*Максимальный показатель полученный в лабораторных условиях»; плотность 800 кг/м3 (самая лёгкая из TEFIX). Таблицы расхода нет. Есть зимняя версия.
A15: Perel | B15: Тёплые (теплоизоляционные) кладочные растворы | C15: да | D15: Perel TKS 2020 | E15: Теплая кладочная смесь Perel TKS 2020, 25 кг | F15: 1 | G15: Теплая смесь Perel TKS 2020 (усиленная) применяется в качестве раствора для кладки теплых блоков, таких как крупноформатные поризованные керамические блоки, поризованные керамические камни, арболит и т.п.. | H15: Бумажные крафт-мешки: 25 кг | L15: — | N15: https://td-perel.ru/catalog/teplaya-kladochnaya-smes/teplaya-kladochnaya-smes-2020/ | O15: Короткое описание упоминает арболит, полное — нет. «Выход раствора 1,0 – 1,1 л/кг» — это выход, не расход, поэтому consumption пуст. Нанесение по СП 70.13330.2012 (свод правил на кладку, не стандарт продукта — в normative не ставил). Зимней модификации на карточке нет. В конце ядра служебные строки «SEOTEG01 / arbolit».
A16: Perel | B16: Тёплые (теплоизоляционные) кладочные растворы | C16: да | D16: Perel TKS 6020 | E16: Теплая кладочная смесь Perel TKS 6020, 20 кг | F16: 1 | G16: Теплая смесь Perel TKS 6020 (экономичная) применяется в качестве раствора для каменной и (или) кирпичной кладки материалов с повышенными теплоизоляционными свойствами, таких как крупноформатные поризованные керамические блоки, поризованные керамические камни. | H16: Бумажные крафт-мешки: 20 кг | L16: — | N16: https://td-perel.ru/catalog/teplaya-kladochnaya-smes/teplaya-kladochnaya-smes-20208216/ | O16: Раздел «Описание» пуст, назначение — в коротком описании. Выход 1,3 - 1,4 л/кг (не расход). Нанесение по СП 70.13330.2012. Зимней модификации на карточке нет.
A17: Perel | B17: Тёплые (теплоизоляционные) кладочные растворы | C17: да | D17: Perel TKS 8020 | E17: Теплая кладочная смесь Perel TKS 8020, 17.5 кг | F17: 1 | G17: Применяется для исключения мостиков холода при кладке теплых блоков (керамические крупноформатные блоки и т.п.) | H17: Бумажные крафт-мешки: 17,5 кг | I17: Расход сухой смеси на 1 блок (кг) 51 - (510×250×219 мм) 1,4 - 1,5 44 - (440×250×219 мм) 1,2 - 1,3 38 - (380×250×219 мм) 1 - 1,1 30 - (250×300×219 мм) 0.8 - 0,9 25 - (250×380×219 мм) 1 - 1,1 12 - (120×500×219 мм) 0,6 - 0,7 | L17: есть | N17: https://td-perel.ru/catalog/teplaya-kladochnaya-smes/perel-tks-8020/ | O17: Есть зимняя модификация: «8520 – «зима»», 17.5 кг, «от -5 °С до +10 °С» (лето 8020 — от +5 °С до +30 °С). Теплопроводность в преимуществах «< 0,17 Вт/м*К», в характеристиках «0,17 Вт/м∙°С». Выход «26 - 28 л» без «/кг» (видимо на мешок). В названии «17.5 кг» (точка), в тексте «17,5 кг». В таблице расхода опечатка «0.8 - 0,9». Расход дан на 1 блок по форматам (multi-line цитата таблицы).
A18: Основит | B18: Тёплые (теплоизоляционные) кладочные растворы | C18: да | D18: Основит Путформ MC114 | E18: Раствор кладочный теплоизоляционный зимний Основит Путформ MC114 F 20 кг | F18: 4 | G18: Теплоизоляционный кладочный раствор ОСНОВИТ ПУТФОРМ МС114 F зимний предназначен для кладки стен из лёгких пустотелых керамических блоков, блоков из бетона на пористых заполнителях при температуре окружающей среды и основания от -10 до + 10°С. | H18: Мешок 20кг | I18: Размер блока Расход смеси (готовый р-р), л Расход смеси (сухая смесь), кг 510x250x219 2,3 2,0 440x250x219 2,2 1,9 380x250x219 1,95 1,7 | J18: Рекомендуемая толщина шва кладки 5-15 мм | K18: L M50, ГОСТ Р 58272-2018 | L18: есть | M18: серый | N18: https://osnovit.ru/catalog/kladochnye-rastvory/putform-mc114-f-zimniy-teploizolyatsionnyy-kladochnyy-rastvor/ | O18: Зимняя модификация MC114 (летняя — карточка MC114 в этой пачке). Оговорка: возможна фасовка в мешок «ПУТФОРМ МС114» со стикером «зимний». Значения температур записаны небрежно («-50°С…+65°», «- 10°С…+10° ºС»). Срок хранения 6 месяцев (у летней 12/24).
A19: Основит | B19: Тёплые (теплоизоляционные) кладочные растворы | C19: да | D19: Основит Путформ MC114 L | E19: Раствор кладочный теплоизоляционный высокоэффективный Основит Путформ MC114 L 20 кг | F19: 1 | G19: Высокоэффективный теплоизоляционный кладочный раствор ОСНОВИТ ПУТФОРМ MC114 L предназначен для кладки стен из материалов с повышенными теплоизоляционными свойствами, а именно из лёгких пустотелых керамических блоков и блоков из бетона на пористых заполнителях. | H19: Вес упаковки 20 кг | I19: Размер блока Расход смеси (готовый р-р), л Расход смеси (сухая смесь), кг 510x250x219 2,3 1,6 440x250x219 2,2 1,5 380x250x219 1,95 1,3 | J19: Рекомендуемая толщина шва кладки 5-15 мм | K19: L M50, ГОСТ Р 58272-2018 | L19: — | M19: серый | N19: https://osnovit.ru/catalog/kladochnye-rastvory/osnovit-putform-mc114-l-vysokoeffektivnyy-teploizolyatsionnyy-/ | O19: Отдельная модель «L» (высокоэффективная: ниже теплопроводность 0,18-0.20, плотность 800-900, выход 28-30 л) — вынесена в свой series_key, хотя по линейке это модификация MC114; при склейке решить, держать ли отдельной позицией. В значении теплопроводности смешаны запятая и точка («0,18-0.20»). Зимней версии MC114 L в тексте нет.
A20: Основит | B20: Расшивка швов кирпичной кладки | C20: да | D20: Основит Бриксэйв XC30 | E20: Раствор цветной для расшивки швов Основит Бриксэйв XC30 20 кг | F20: 1 | G20: Раствор для расшивки швов ОСНОВИТ БРИКСЭЙВ ХС30 предназначен для отделки швов: | H20: 20 кг | I20: 5,0 | J20: 5-30 мм | L20: — | M20: 22 цвета | N20: https://osnovit.ru/catalog/rasshivki/brikseyv-xc30/ | O20: consumption_quote «5,0» — кг на 1 м² кладки (кирпич 250x120x65) при глубине и ширине шва 10 мм (подпись разбита на строки). В преимуществах «22 цветовых решений», в характеристиках «22 цвета». Пометка «Колеровка» у заголовка. Пересекается с сайтом «Цветные кладочные смеси» (цветная расшивка). Документы «Описание», «Техническая карта» — без ссылок во входе.
A21: Dauer | B21: Клей для блоков и газобетона | C21: да | D21: Dauer QUADER D600 | E21: Dauer QUADER D600 клей для блоков усиленный | F21: 1 | G21: Для возведения стен и перегородок из блоков на основе газо- и пенобетона, силикатного пенобетона, полистиролбетона и других ячеистых блоков. | H21: 25 кг, 40 кг | I21: Расход раствора при слое шва 2 мм | J21: 2-5 мм | K21: ГОСТ Р 58272 | L21: есть | N21: https://dauer.ru/catalog/montazhnye-i-kladochnye/block-d600-kley-montazhnyy/ | O21: Полное наименование «Dauer Quader Блок (Block) D600». Расход — таблицей при шве 2 мм, «Количество на 1 м 3» кладки по формату блока: 15–19 кг (первые 4 пары characteristics — формат блока → кг на 1 м3). Зимняя версия — до -10 °С / -15 °С «в зависимости от версии продукта». Документ назван «Клей монтажный тонкошовный (лето и зима)».
A22: Perel | B22: Клей для блоков и газобетона | C22: да | D22: Perel Blokus | E22: Perel Blokus 25 кг, серый | F22: 4 | G22: Для кладки блоков и плит из ячеистого бетона, пенобетона, газосиликата и газобетона и т.п.. Исключает появление «мостиков холода» в швах кладки блоков благодаря тонкослойному кладочному шву 2-5 мм. | H22: Бумажные крафт-мешки - 25 кг. | I22: 8-9 кг/м 2 стандартного блока 600*200*300 при слое кладки 5 мм. | J22: благодаря тонкослойному кладочному шву 2-5 мм | L22: — | N22: https://td-perel.ru/catalog/montazhnyy-kley/perel_blokus_25_kg_seryy/ | O22: Тот же продукт, что Blokus 40 кг серый (0340) и белые Blokus 0332/0334 — характеристики одинаковые. Морозостойкость на карточке F50 (на подборке белого клея заявлено F100). ГОСТ на карточке нет; «для внутренних и наружных работ» есть только на подборке kley-gaz. Пара «Коэффициент паропроницаемости» на странице есть, в characteristics не вошла.
A23: Основит | B23: Клей для блоков и газобетона | C23: да | D23: Основит PRO Клей для блоков | E23: Клей для блоков Основит PRO | F23: 1 | G23: Клей для блоков ОСНОВИТ PRO используется в тонкослойной кладке стен и перегородок. Предназначен для пазовых и беспазовых блоков и плит на основе ячеистого бетона (пено- и газобетон), газосиликата и силиката. | H23: 20 кг | I23: 1,3 кг/м² | J23: Для тонкого шва от 2 до 5 мм | L23: — | N23: https://osnovit.ru/catalog/osnovit-pro/kley-dlya-blokov-osnovit-pro/ | O23: Сухость — из характеристики «Расход воды на 1 кг сухой смеси» (фразы «смесь сухая» нет). Основа (цемент) не названа. Есть таблица расхода по размерам блоков (напр. 625*250*150: 0,75 кг на блок, 8 кг на м² стены, 32 кг на м³). ГОСТ не указан. Нет pdf во входе.
A24: Основит | B24: Клей для блоков и газобетона | C24: да | D24: Основит Селформ MC112 | E24: Клей монтажный зимний Основит Селформ MC112 F 20 кг | F24: 2 | G24: ОСНОВИТ СЕЛФОРМ MC112 F зимний клей монтажный предназначен для кладки стен и перегородок из блоков и плит на основе ячеистого бетона (пено- и газобетон), газосиликата и силиката при температуре окружающей среды и основания от -10 до + 10°С . | H24: Вес упаковки 20 кг | I24: Расход смеси на 1 м 3 блоков (блоки из ячеистых бетонов 20*30*60 см, шов 3 мм) 26 кг | J24: Рекомендуемая толщина слоя 1-5 мм | K24: Т M100, ГОСТ Р 58272-2018 | L24: есть | M24: серый | N24: https://osnovit.ru/catalog/montazhnye-klei/selform-mc-112-f/ | O24: Зимняя модификация MC112. Оговорка: возможна фасовка в мешок «СЕЛФОРМ МС112» со стикером «зимний». Расход дан «на 1м² блоков … 8 кг», у летней — «на 1 м 3 блоков … 26 кг» (разная база, не сравнивать напрямую). Строка «Температура эксплуатации» повторена дважды в разной записи. Срок хранения 6 месяцев.
A25: Основит | B25: Клей для блоков и газобетона | C25: да | D25: Основит Техно MC112 | E25: Клей монтажный зимний Основит Техно MC112 F 40 кг | F25: 2 | G25: Клей монтажный ОСНОВИТ ТЕХНО MC112 F предназначен для кладки стен и перегородок из блоков и плит на основе ячеистого бетона (пено- и газобетон), газосиликата и силиката при температуре окружающей среды и основания от -10 до + 10°С. | H25: 40 кг | I25: 26 кг | J25: 2-5 мм | K25: Т M100, ГОСТ Р 58272-2018 | L25: есть | N25: https://osnovit.ru/catalog/montazhnye-klei/kley-montazhnyy-osnovit-tekhno-mc112-f-zimniy/ | O25: Зимняя модификация Техно MC112. Марка/ГОСТ на карточке не указаны (у летнего — «Т M100, ГОСТ Р 58272-2018»), сухость — по «Расход воды на 1 кг сухой смеси». Расход 26 кг на 1 м3 и 8 кг на 1 м2 (блоки 20*30*60 см, шов 3 мм) — названия разорваны переносом, взяты фрагменты. Срок хранения 12 мес. (бумажный) / 24 мес. (пластиковый мешок). Бейджа «Зима» на странице нет. На карточке Брикформ MC11/1 F сос
A26: Perel | B26: Гипсовый монтажный клей (ГКЛ, ПГП) | C26: да | D26: Perel Gipsel | E26: Perel Gipsel, 30 кг, серый, гипсовый клей | F26: 2 | G26: Сухая монтажная смесь на основе гипсового вяжущего, минеральных и полимерных добавок для монтажа перегородок из гипсовых пазогребневых плит, крепления гипсовых элементов, для бескаркасного монтажа гипсокартонных и гипсоволокнистых листов (ГКЛ, ГВЛ), листов теплоизоляции к вертикальным внутри помещений с нормальной влажностью | H26: Бумажные крафт-мешки по 30 кг. | J26: Толщина вертикальных и горизонтальных швов должна быть не более 2 мм. | L26: — | N26: https://td-perel.ru/catalog/montazhnyy-kley/gipsovyy-kley-perel-gipsel/ | O26: Описание совпадает с Gipsel белый (0331); в характеристиках только артикул и цвет (у белого ещё температура, адгезия 0,3 МПа, открытое время 5 мин). Расход не указан.
A27: Основит | B27: Гипсовый монтажный клей (ГКЛ, ПГП) | C27: да | D27: Основит PRO клей гипсовый монтажный | E27: Клей гипсовый монтажный Основит PRO 20 кг | F27: 1 | G27: Клей монтажный гипсовый ОСНОВИТ PRO Предназначен для монтажа перегородок из пазогребневых плит, ремонта пазогребневых плит, крепления гипсовых элементов декора и отделки, для бескаркасного монтажа гипсокартонных и гипсоволокнистых листов (ГКЛ и ГВЛ), приклеивания теплоизоляционных материалов. | H27: Вес упаковки 20 кг | I27: Расход сухой смеси при монтаже ПГП на 1 м2 1,5-2 кг | J27: Рекомендуемая толщина слоя при монтаже ПГП 2-3 мм | K27: Т M100, ГОСТ Р 58272-2018 | L27: — | M27: серый | N27: https://osnovit.ru/catalog/osnovit-pro/kley-montazhnyy-gipsovyy-osnovit-pro/ | O27: Странность: для гипсового клея указана классификация кладочной смеси «Т M100, ГОСТ Р 58272-2018». Без кода модели — ключ по линейке PRO. Цвет «серый». Расход воды без единиц («0,43-0,45»). Карточка в разделах «Монтажные клеи» и «Основит PRO».
A28: Dauer | B28: Цементно-песчаные смеси М150–М400, пескобетон | C28: да | D28: Dauer М-150 Универсальная | E28: Dauer® Сухая смесь М-150 Универсальная | F28: 1 | G28: Сухая смесь универсальная предназначена для возведения стен и перегородок из кирпича и мелкоштучных элементов, для работ по заделке полостей, выбоин и трещин, производства различных монтажных и штукатурных работ, а также для укладки тротуарной плитки. | H28: 30 кг, 40 кг, 50 кг | I28: 19 кг/м² | J28: Толщина горизонтальных швов кладки – 10 -15 мм, вертикальных – 8 -10 мм. | K28: ГОСТ 28013-98 | L28: есть | N28: https://dauer.ru/catalog/tsementno-peschanye-smesi/sukhaya_smes_m_150_universalnaya/ | O28: Универсальная ЦПС М150: кладка, монтаж, штукатурка, тротуарная плитка. base_quote — название раздела каталога, своей фразы об основе на странице нет. Зимние модификации -10/-15°С (на сайте значение «от * °С до +30 °С»). Расхождение: в «Тип основания» прочность не менее 10 МПа, в подготовке основания — не менее 15 МПа. Расход 19 кг/м² указан на слой 10 мм.
A29: Dauer | B29: Цементно-песчаные смеси М150–М400, пескобетон | C29: да | D29: Dauer М-150 Штукатурная | E29: Dauer® Сухая смесь М-150 Штукатурная | F29: 1 | G29: Сухая смесь штукатурная предназначена для оштукатуривания стен из бетона, кирпича, камня. | H29: на 1 мешок 50 кг | I29: 19 кг/м² | J29: 10 – 30 мм | K29: ГОСТ 28013-98 | L29: есть | N29: https://dauer.ru/catalog/tsementno-peschanye-smesi/sukhaya_smes_m_150_shtukaturnaya/ | O29: Сомнение в типе: по составу это ЦПС М150 (masonry_universal_cps, раздел «Цементно-песчаные смеси»), по назначению — только штукатурка (plaster_cement). В характеристиках фасовки нет; «на 1 мешок 50 кг» взято из раздела «Выполнение работ». Расхождение по слою: в характеристиках 10–30 мм, в разделе работ «слоем 20 - 50 мм». Расход 19 кг/м² указан на слой 10 мм. Зимняя версия есть (температура «от *
A30: Dauer | B30: Цементно-песчаные смеси М150–М400, пескобетон | C30: да | D30: Dauer М-200 Монтажно-кладочная | E30: Dauer® Сухая смесь М-200 Монтажно-кладочная | F30: 1 | G30: Сухая смесь монтажно-кладочная предназначена для выполнения общестроительных работ: устройство "мокрых" стяжек; заделка швов, трещин, выбоин, углублений; возведение стен и конструкций из полнотелого рядового кирпича, полнотелых бетонных блоков и природного камня. | H30: на 1 мешок 50 кг | I30: 20 кг/м² | J30: Толщина горизонтальных швов кладки – 10-15 мм, вертикальных – 8-10 мм. | K30: ГОСТ 28013-98 | L30: есть | N30: https://dauer.ru/catalog/tsementno-peschanye-smesi/sukhaya_smes_m_200_montazhno_kladochnaya/ | O30: В характеристиках фасовки нет; «на 1 мешок 50 кг» взято из раздела работ. Фразы «для наружных/внутренних работ» нет. Стяжка по разделу работ — слоем 30-80 мм. Зимние модификации -5/-10/-15°С (значение «от * °С»). Расход 20 кг/м² указан на слой 10 мм.
A31: Dauer | B31: Цементно-песчаные смеси М150–М400, пескобетон | C31: да | D31: Dauer М-300 Пескобетон | E31: Dauer® Сухая смесь М-300 Пескобетон | F31: 1 | G31: Сухая смесь пескобетон предназначена для выполнения общестроительных работ: устройство высокопрочных стяжек ("мокрого" типа); заделка швов, трещин, выбоин, углублений; крепление металлических элементов и монтаж железобетонных конструкций; возведение стен и конструкций из полнотелого рядового кирпича, полнотелых бетонных блоков и природного камня. | H31: 30 кг, 40 кг, 50 кг | I31: 20 кг/м² | J31: Толщина слоя нанесения составляет 30-200 мм | K31: ГОСТ 28013-98 | L31: есть | N31: https://dauer.ru/catalog/tsementno-peschanye-smesi/sukhaya_smes_m_300_peskobeton/ | O31: Пескобетон М300. Можно отнести и к floor_screed (основное применение — стяжки), но по классификатору оставлен в ЦПС. С щебнем 5–20 мм в соотношении 1:2 даёт бетонную смесь. Фразы «для наружных/внутренних работ» нет. Зимние модификации -10/-15°С. Расход 20 кг/м² указан на слой 10 мм.
A32: Dauer | B32: Цементно-песчаные смеси М150–М400, пескобетон | C32: да | D32: Dauer М-400 Пескобетон высокопрочный | E32: Dauer® Сухая смесь М-400 Пескобетон высокопрочный | F32: 1 | G32: Сухая смесь пескобетон предназначена для выполнения общестроительных работ: устройство высокопрочных стяжек ("мокрого" типа); заделка швов, трещин, выбоин, углублений; крепление металлических элементов и монтаж железобетонных конструкций; возведение стен и конструкций из полнотелого рядового кирпича, полнотелых бетонных блоков и природного камня. | H32: 40 кг | I32: 20 кг/м² | J32: слоем 30-70 мм | K32: ГОСТ 28013-98 | L32: есть | N32: https://dauer.ru/catalog/tsementno-peschanye-smesi/sukhaya-smes-m-400-peskobeton-vysokoprochnyy/ | O32: Описание назначения слово в слово совпадает с М-300; отличия — марка М400 и фасовка (только 40 кг). В разделе работ: стяжка слоем 30-70 мм, отмостка, мощение, заполнение швов. Фразы «для наружных/внутренних работ» нет. Расход 20 кг/м² указан на слой 10 мм.
A33: Perel | B33: Цементно-песчаные смеси М150–М400, пескобетон | C33: да | D33: Perel М-150 Базовый | E33: М-150 Базовый, 50 кг | F33: 1 | G33: Цементно-песчаная смесь с пластифицирующими добавками. Рекомендуется для выполнения кладочных работ рядовым кирпичом. | H33: Бумажные крафт-мешки по 50 кг. | L33: есть | N33: https://td-perel.ru/catalog/universalnye-smesi/m-150-bazovyy/ | O33: Марка М150 — только в названии; характеристик (прочность, расход) нет, артикул «-». Упомянута модификация «зима» без отдельного артикула. Бренд Perel в названии не стоит (упомянута грунтовка «PEREL»). В инструкции фраза про «поверхности пола» — похоже, текст скопирован с другой карточки. Нанесение по СП 70.13330.2012.
A34: Perel | B34: Цементно-песчаные смеси М150–М400, пескобетон | C34: да | D34: Perel М-150 Универсальный | E34: М-150 Универсальный, 40 кг | F34: 1 | G34: Применяется для штукатурно-кладочных работ. | H34: Бумажные крафт-мешки по 40 кг. | K34: СП 70.13330.2012 | L34: есть | N34: https://td-perel.ru/catalog/universalnye-smesi/m-150-universalnyy/ | O34: Блок «Характеристики» на странице пуст (только Артикул «-»); пары кроме артикула взяты из описания. Расход и толщина слоя не указаны. Зимняя версия упомянута в тексте («с модификацией «зима»»), отдельной карточки в пачке нет. СП 70.13330.2012 — свод правил на производство работ, а не стандарт на смесь. Описание шире краткого: «Применяется для выравнивания поверхностей по минеральным основаниям (бе
A35: Perel | B35: Цементно-песчаные смеси М150–М400, пескобетон | C35: да | D35: Perel М-300 Пескобетон | E35: М-300, 50 кг | F35: 1 | G35: Сухая строительная смесь Пескобетон М 300 применяется как мелкозернистый бетон для заливки фундаментов, изготовления высокопрочных бетонных стяжек различной толщины, в качестве несущего слоя полов, при обустройстве жилых, общественных и производственных помещений, гаражей, зон повышенного потока людей, при монтажно-кладочных работах, для возведения и ремонта бетонных стен и оснований. | H35: Бумажные крафт-мешки по 50 кг. | J35: Минимальная толщина слоя 25мм. | L35: есть | N35: https://td-perel.ru/catalog/universalnye-smesi/m-300/ | O35: Пескобетон; лежит в разделе «Универсальные смеси», по тексту в основном стяжка и фундамент (подошёл бы и floor_screed), выбран masonry_universal_cps как пескобетон. Название на странице «М-300, 50 кг», в тексте «Пескобетон М300» и «Пескобетон М 300» (разное написание). Блок «Характеристики» пуст (Артикул «-»), пары взяты из описания. Расход не указан. Основа явно не названа. Зимняя модификация упо
A36: Dauer | B36: Штукатурки гипсовые | C36: да | D36: Dauer SLIDER 36 | E36: Dauer SLIDER® 36 Штукатурка гипсовая универсальная серая | F36: 2 | G36: Для машинного и ручного выравнивания стен: сплошного (от 5 до 50 мм) и частичного при локальном выравнивании (до 60 мм), выравнивания потолков (до 10 мм) – внутри помещений с умеренной влажностью под последующую отделку (финишное тонкослойное шпатлевание, оклейку обоями, многослойное окрашивание). | H36: 30 кг. | I36: 9 – 10 кг/м² | J36: сплошного (от 5 до 50 мм) | K36: ГОСТ Р 58279 | L36: — | N36: https://dauer.ru/catalog/shtukaturki/slider-36/ | O36: Серая; белая версия — SLIDER 36W, у неё тот же series_key. Расход 9–10 кг/м² указан на слой 10 мм. Декларация РОСС RU (кода товара в имени файла нет) не включена. Полное наименование «Dauer Slider Интерьер (Interier) 36».
A37: Dauer | B37: Штукатурки гипсовые | C37: да | D37: Dauer SLIDER 37 | E37: Dauer SLIDER® 37 Штукатурка гипсовая теплая армированная | F37: 2 | G37: Для машинного и ручного выравнивания стен: сплошного (от 3 до 50 мм) и частичного, при локальном выравнивании (до 80 мм), для выравнивания потолков (до 30 мм), внутри помещений с умеренной влажностью под последующую отделку (финишное тонкослойное шпатлевание, оклейку обоями, многослойное окрашивание). | H37: 30 кг. | I37: 0,8 кг/м² | J37: сплошного (от 3 до 50 мм) | K37: ГОСТ Р 58279-2024 | L37: — | N37: https://dauer.ru/catalog/shtukaturki/slider-37/ | O37: «Тёплая армированная» гипсовая штукатурка, не кладочный раствор. Техкарта подписана «…с перлитом». В особенностях опечатка сайта «Идеальное качество без шатлевания». Расход 0,8 кг/м² указан на слой 1 мм. Белая версия — 37W, у неё тот же series_key. Полное наименование «Dauer Slider Интерьер (Interier) 37».
A38: Dauer | B38: Штукатурки гипсовые | C38: да | D38: Dauer SLIDER 38 | E38: Dauer SLIDER® 38 Штукатурка гипсовая легкая с перлитом | F38: 2 | G38: Для машинного и ручного выравнивания стен: сплошного (от 3 до 50 мм) и частичного, при локальном выравнивании (до 80 мм), для выравнивания потолков (до 30 мм), внутри помещений с умеренной влажностью под последующую отделку (шпатлевание, оклейку обоями, многослойное окрашивание). | H38: 30 кг. | I38: 0,8 кг/м² | J38: сплошного (от 3 до 50 мм) | K38: ГОСТ Р 58279-2024 | L38: — | N38: https://dauer.ru/catalog/shtukaturki/slider-38/ | O38: Расхождение: в описании сплошной слой от 3 до 50 мм, в характеристиках «Толщина слоя при сплошном нанесении 5-50 мм». Расход 0,8 кг/м² указан на слой 1 мм. Белая версия — 38W, у неё тот же series_key. Полное наименование «Dauer Slider Интерьер (Interier) 38».
A39: Dauer | B39: Штукатурки гипсовые | C39: да | D39: Dauer SLIDER 39 | E39: Dauer SLIDER® 39 Штукатурка гипсовая универсальная влагостойкая | F39: 1 | G39: Для машинного и ручного выравнивания стен: сплошного (от 5 до 50 мм) и частичного при локальном выравнивании (до 80 мм), для выравнивания потолков (до 20 мм), внутри помещений с нормальной и повышенной влажностью под последующую отделку: финишное тонкослойное шпатлевание, оклейку обоями, многослойное окрашивание, облицовку керамической плиткой малого формата (размер грани не более 30 см) с тщательной затиркой межплиточных швов. | H39: 30 кг. | I39: 10 – 11 кг/м² | J39: сплошного (от 5 до 50 мм) | K39: ГОСТ Р 58279 | L39: — | N39: https://dauer.ru/catalog/shtukaturki/slider-39/ | O39: Влагостойкая гипсовая. Расхождение по воде: в характеристиках 0,30–0,35 л на 1 кг, в разделе «Выполнение работ» 0,25–0,28 л (7,5–8,5 л на мешок 30 кг). Ссылка в документах подписана «DAUER SLIDER 312 Штукатурка цементная мелкофракционная гладкая» — похоже на ошибку сайта. Есть «Рекомендательное письмо SLIDER INTERIER 39». Расход 10–11 кг/м² указан на слой 10 мм.
A40: Perel | B40: Штукатурки гипсовые | C40: да | D40: Perel Plast | E40: Perel Plast, 30 кг, белая, пластичная гипсовая штукатурка с увеличенным временем жизни | F40: 1 | G40: Пластичная гипсовая штукатурная смесь на основе природного гипса, минерального наполнителя и полимерных добавок, для выравнивания стен (до 50 мм) из бетона, газобетона, кирпича и каменных поверхностей ручным способом, внутри жилых и общественных сухих помещений с нормальным уровнем температуры и влажности. | H40: Бумажные крафт-мешки по 30 кг. | J40: Рекомендуемый слой нанесения составляет 5-50мм за один проход. | L40: — | N40: https://td-perel.ru/catalog/gipsovaya-shtukaturka/gipsovaya-shtukaturka-plastichnaya-perel-plast-belaya-30-kg/ | O40: Расхождение: лид «Для ручного или машинного нанесения», описание — «ручным способом». Расход не указан. Срок хранения 6 месяцев. Есть раздел «Видеообзоры» (в полном тексте только заголовок). В «Характеристиках» только артикул.
A41: Perel | B41: Штукатурки гипсовые | C41: да | D41: Perel TeploPlast | E41: Perel TeploPlast, 30 кг, белая, облегченная гипсовая штукатурка с перлитом | F41: 1 | G41: Экологически чистая штукатурная смесь повышающая звуко- и теплоизоляцию на основе природного гипса с использованием легкого минерального наполнителя (перлита) и специальных химических добавок, для выравнивания значительных перепадов потолков и стен из бетона, газобетона, кирпича и каменных поверхностей ручным способом, внутри жилых и общественных сухих помещений с нормальным уровнем влажности. | H41: Бумажные крафт-мешки по 30 кг. | J41: Рекомендуемый слой нанесения составляет 5-50мм за один проход. | L41: — | N41: https://td-perel.ru/catalog/gipsovaya-shtukaturka/gipsovaya-shtukaturka-oblegchennaya-perel-teploplast-belaya-30kg/ | O41: Расход не указан. Воды 12,9–13,8 л на мешок 30 кг (у Perel Plast 8–9 л) — для перлитовой смеси возможно, но число стоит сверить с техлистом. Срок хранения 6 месяцев. В «Характеристиках» только артикул.
A42: Основит | B42: Штукатурки гипсовые | C42: да | D42: Основит PRO Штукатурка гипсовая универсальная | E42: Штукатурка гипсовая универсальная белая Основит PRO 30 кг | F42: 1 | G42: Гипсовая штукатурка ОСНОВИТ PRO предназначена для выравнивания стен и потолков в помещениях с нормальной влажностью. | H42: 30 кг | I42: 9-10 кг/м² | J42: 3-30мм | K42: 90/3,0, ГОСТ Р 58279-2018 | L42: — | M42: Белый цвет | N42: https://osnovit.ru/catalog/osnovit-pro/shtukaturka-gipsovaya-uni-pro/ | O42: В преимуществах «Экономичный расход 9 кг на 1 квадратный метр», в характеристиках «9-10 кг/м²» при слое 10 мм. Раздел «Документация» пуст (тех. карты нет). Блок «С этим материалом применяется» пуст. Нет pdf во входе.
A43: Основит | B43: Штукатурки гипсовые | C43: да | D43: Основит Гипсвэлл PG25 | E43: Штукатурка гипсовая универсальная белая Основит Гипсвэлл PG25 W 30 кг | F43: 2 | G43: ОСНОВИТ ГИПСВЭЛЛ PG25 W — универсальная гипсовая штукатурка белого цвета для выравнивания стен и потолков внутри помещений с нормальной влажностью. | H43: 30 кг | I43: 8-9 кг/м² | J43: Слой от 3 до 80 мм | K43: 90/3,0. Соответствует ГОСТ Р 58279-2024 | L43: — | N43: https://osnovit.ru/catalog/shtukaturki/shtukaturka-gipsovaya-universalnayabelaya-osnovit-gipsvell-pg-25-w/ | O43: Белая версия Гипсвэлл PG25 (пара с серой — один series_key). Расход при слое 10 мм. В документации две техкарты, одна — «Техническая карта Майкоп» (вероятно, по площадке производства). Расход воды 0,4-0,5 л (у серой 0,47-0,53 л).
A44: Основит | B44: Штукатурки гипсовые | C44: да | D44: Основит Техно PG26/1 M | E44: Штукатурка гипсовая Основит Техно PG26/1 M 30 кг | F44: 2 | G44: ОСНОВИТ ТЕХНО PG26/1 M — гипсовая штукатурка серого цвета для выравнивания стен и потолков внутри помещений с нормальной влажностью. | H44: 30 кг | I44: 10 - 11 кг/м² | J44: 3-30 мм | K44: ГОСТ Р 58279-2024 | L44: — | M44: серый | N44: https://osnovit.ru/catalog/shtukaturki/gipsovaya-shtukaturka-osnovit-tekhno-pg26-1-m/ | O44: Серая; белый аналог — PG26/1 MW (id ...gipsovaya-shtukaturka-belaya-osnovit-tekhno-pg26-1-mw). Срок хранения 9/18 мес. В «С этим материалом применяется» — шпаклёвка чужой марки «Стройбриг Генфир».
A45: Основит | B45: Штукатурки гипсовые | C45: да | D45: Основит Техно PK27 M | E45: Штукатурка универсальная влагостойкая Основит Техно PK27 M 30 кг | F45: 1 | G45: ОСНОВИТ ТЕХНО PK27 M — универсальная влагостойкая гипсовая штукатурка для выравнивания стен и потолков в помещениях с нормальной и повышенной влажностью. | H45: 30 кг | I45: 10-11 кг/м² | J45: 3-30 мм | K45: ГОСТ Р 58279-2024 | L45: — | M45: Серый, светло-серый | N45: https://osnovit.ru/catalog/shtukaturki/shtukaturka-universalnaya-vlagostoykaya-tekhno-pk27-m/ | O45: Влагостойкая гипсовая (код PK, но основа — гипс по тексту). Подпись «толщина слоя без использования» на сайте оборвана (чего — не сказано), значение 3-60 мм. Белый родственник — PK271 MW (другой код и другая прочность).
A46: Основит | B46: Штукатурки гипсовые | C46: да | D46: Основит Техно PK271 MW | E46: Штукатурка универсальная влагостойкая белая Основит Техно PK271 MW 30 кг | F46: 1 | G46: ОСНОВИТ ТЕХНО PK271 MW — белая влагостойкая гипсовая штукатурка для выравнивания стен и потолков в помещениях с нормальной и повышенной влажностью. | H46: 30 кг, 40 кг | I46: 10 - 11 кг/м² | J46: 3-30 мм | K46: ГОСТ Р 58279-2024 | L46: — | M46: Природно-белый* | N46: https://osnovit.ru/catalog/seria-techno/shtukaturka-universalnaya-vlagostoykaya-belaya-tekhno-pk271-mw/ | O46: В названии 30 кг, в характеристиках «30 кг, 40 кг». Нет кнопки «Купить». Класс 90/3,5 против 90/5,0 у PK27 M — отдельный продукт, не просто белый цвет; series_key оставлен свой. Сноска «*» у цвета без расшифровки в тексте.
A47: Dauer | B47: Штукатурки цементные и цементно-известковые (вкл. обрызг) | C47: да | D47: Dauer SLIDER 301 | E47: Dauer SLIDER® 301 Штукатурка цементно-известковая выравнивающая облегченная | F47: 1 | G47: Штукатурка цементно-известковая выравнивающая облегченная SLIDER® 301 предназначена для ручного и механизированного высококачественного выравнивания (слой 5 – 40 мм) поверхности фасадов зданий и сооружений, стен внутри всех видов помещений в т.ч. влажных и неотапливаемых: подвалы, балконы и лоджии, паркинги, лестничные пролеты, марши, склады, другие помещения с переменной влажностью. | H47: 40 кг. | I47: 12,5 кг/м2 | J47: слой 5 – 40 мм | K47: ГОСТ 33083 | L47: есть | N47: https://dauer.ru/catalog/shtukaturki/slider-fasad-301/ | O47: Расход 12,5 кг/м2 указан на слой 10 мм. Зимняя версия от -10°С (документ «лето и зима»). Подходит для штукатурных станций 220/380 В. Полное наименование «Dauer Slider Фасад (Fasad) 301».
A48: Dauer | B48: Штукатурки цементные и цементно-известковые (вкл. обрызг) | C48: да | D48: Dauer SLIDER 302 | E48: Dauer SLIDER® 302 Штукатурка цементно-известковая гладкая | F48: 1 | G48: Штукатурка цементно-известковая гладкая Dauer SLIDER® 302 предназначена для ручного и механизированного высококачественного выравнивания (слой 5 – 40 мм) поверхности фасадов зданий и сооружений, стен внутри всех видов помещений в т.ч. влажных и неотапливаемых: подвалы, балконы и лоджии, паркинги, лестничные пролеты, марши, склады, другие помещения с переменной влажностью. | H48: 25 кг. | I48: 12,5 кг/м2 | J48: слой 5 – 40 мм | K48: ГОСТ 33083 | L48: есть | N48: https://dauer.ru/catalog/shtukaturki/slider-fasad-302/ | O48: Расход 12,5 кг/м2 указан на слой 10 мм. Есть зимняя версия (по характеристикам от -10°С). Полное наименование «Dauer Slider Фасад (Fasad) 302».
A49: Dauer | B49: Штукатурки цементные и цементно-известковые (вкл. обрызг) | C49: да | D49: Dauer SLIDER 31 Slim | E49: Dauer SLIDER® 31 Штукатурка цементная мелкофракционная гладкая | F49: 1 | G49: Для ручного и механизированного выравнивания слоем от 3 мм. (локально) до 30 мм. поверхности фасадов, стен внутри всех видов помещений, в т.ч. влажных и неотапливаемых: подвалы, лоджии, паркинги, лестничные пролеты, марши, склады, душевые и ванные комнаты. | H49: 25 кг, 40 кг | I49: 12 - 13 кг/м² | J49: слоем от 3 мм. (локально) до 30 мм. | K49: ГОСТ 33083-2014 | L49: есть | N49: https://dauer.ru/catalog/shtukaturki/slider-fasad-31-slim-shtukaturka-tsementnaya-melkofraktsionnaya-gladkaya-kp-iii-gost-33083-2014/ | O49: В h1 только «SLIDER® 31»; «Slim/Тонкая» есть в полном наименовании «Dauer Slider Фасад (Fasad) 31 Тонкая (Slim)». Не путать с 31 Фибра. Зимние модификации -10 и -15°С. Странность: в описании «от 3 мм. (локально)», а в характеристиках «Толщина слоя при локальном выравнивании — до 50 мм». Расход 12–13 кг/м² указан на слой 10 мм.
A50: Dauer | B50: Штукатурки цементные и цементно-известковые (вкл. обрызг) | C50: да | D50: Dauer SLIDER 31 Фибра | E50: Dauer SLIDER® 31 Фибра Штукатурка цементная выравнивающая армированная | F50: 1 | G50: Для ручного и механизированного выравнивания (слоем 5 - 40 мм) поверхности фасадов, стен внутри всех видов помещений, в т.ч. влажных и неотапливаемых: подвалы, балконы и лоджии, паркинги, лестничные пролеты, марши, склады, душевые и ванные комнаты. Для ремонта сколов, выбоин, раковин, трещин глубиной до 50 мм. | H50: 25 кг, 40 кг | I50: 14 - 15 кг/м² | J50: слоем 5 - 40 мм | K50: ГОСТ 33083-2014 | L50: есть | N50: https://dauer.ru/catalog/shtukaturki/slider-fasad-31-fibro-shtukaturka-tsementnaya-vyravnivayushchaya-armirovannaya-kp-iii-gost-33083-201/ | O50: Армированная (фибра, «двойное армирование»); в особенностях опечатка сайта «Услиена двойным армированием». Это отдельный продукт от SLIDER 31 Slim (другие фракция и расход), поэтому свой series_key. Прямой фразы «для наружных и внутренних работ» нет, есть только «фасадов, стен внутри». Расход 14–15 кг/м² указан на слой 10 мм. Полное наименование «Dauer Slider Фасад (Fasad) 31 Фибра (Fibro)».
A51: Dauer | B51: Штукатурки цементные и цементно-известковые (вкл. обрызг) | C51: да | D51: Dauer SLIDER 312 | E51: Dauer SLIDER® 312 Штукатурка цементная гладкая с перлитом | F51: 1 | G51: Для высококачественного выравнивания (слой 3 – 40 мм) поверхности фасадов зданий и сооружений, стен внутри всех видов помещений в т.ч. влажных и неотапливаемых: подвалы, балконы и лоджии, паркинги, лестничные пролеты, марши, склады, душевые и ванные комнаты. | H51: 30 кг. | I51: 12 кг/м2 | J51: слой 3 – 40 мм | K51: ГОСТ 33083 | L51: есть | N51: https://dauer.ru/catalog/shtukaturki/slider-312/ | O51: Содержит перлит. Зимняя версия есть (по характеристикам). В документах ещё «SLIDER FASAD 312 .pdf» и «Варса.pdf»: судя по подписям на странице, одно из них — «Рекомендательное письмо», какое именно — неясно; в tech_sheet_urls не включены. Ссылка на документ подписана «Штукатурка цементная мелкофракционная гладкая», в h1 — «гладкая с перлитом». Расход 12 кг/м2 указан на слой 10 мм.
A52: Dauer | B52: Штукатурки цементные и цементно-известковые (вкл. обрызг) | C52: да | D52: Dauer SLIDER 321 | E52: Dauer SLIDER® 321 штукатурка цементная высокопрочная фасадная | F52: 1 | G52: Штукатурка цементная высокопрочная фасадная SLIDER® 321 предназначена для ручного и механизированного высококачественного выравнивания (слой 10 – 40 мм, локально от 5 мм.) поверхности фасадов и цоколей зданий и сооружений, стен снаружи и внутри всех видов помещений в т.ч. влажных и неотапливаемых: подвалы, балконы и лоджии, паркинги, лестничные пролеты, марши, склады, другие помещения с переменной влажностью. | H52: 40 кг. | I52: 16 кг/м2 | J52: слой 10 – 40 мм, локально от 5 мм. | K52: ГОСТ 33083-2014 | L52: есть | N52: https://dauer.ru/catalog/shtukaturki/dauer-slider-321/ | O52: Тип: выравнивающая фасадная и цокольная штукатурка («двойное армирование», под натуральный и искусственный камень и крупноформатный керамогранит). Отнесена к plaster_cement, а не к plaster_facade_base. Странность: зимняя версия «от +5 °С до -10 °С». Расход 16 кг/м2 указан на слой 10 мм.
A53: Dauer | B53: Штукатурки цементные и цементно-известковые (вкл. обрызг) | C53: да | D53: Dauer SLIDER Адгезив | E53: Dauer SLIDER® Адгезив высокопрочный обрызг | F53: 1 | G53: Штукатурный цементный обрызг высокопрочный SLIDER® Адгезив используется для создания шероховатого, структурного, слоя на гладких слабовпитывающих поверхностях и основаниях, для укрепления и выравнивания впитывающей способности комбинированных оснований. | H53: 25 кг. | I53: 1,6 кг/м2 | J53: Толщина наносимого слоя обрызга - 4-10 мм | K53: ГОСТ 33083 | L53: есть | N53: https://dauer.ru/catalog/shtukaturki/slider-fasad-adhesive/ | O53: Цементный обрызг (адгезионный слой) под штукатурку. Красный цвет нужен для «индикации качества нанесения». Есть зимняя версия. Расход 1,6 кг/м2 указан на слой 1 мм. Полное наименование «Dauer Slider Фасад (Fasad) Адгезив (Adhesive)».
A54: Dauer | B54: Штукатурки цементные и цементно-известковые (вкл. обрызг) | C54: да | D54: Dauer SLIDER Легкая | E54: Dauer SLIDER® Легкая Штукатурка цементно-известковая легкая | F54: 1 | G54: Легкая штукатурка для ручного и механизированного высококачественного выравнивания (слой 5 – 50 мм, локально до 80 мм) поверхности фасадов зданий и сооружений, стен внутри всех видов помещений в т.ч. влажных и неотапливаемых: подвалы, балконы и лоджии, паркинги, лестничные пролеты, марши, склады, другие помещения с переменной влажностью, а также для предварительного выравнивания потолков. | H54: 30 кг. | I54: 9 - 10 кг/м2 | J54: слой 5 – 50 мм, локально до 80 мм | K54: ГОСТ 33083 | L54: есть | N54: https://dauer.ru/catalog/shtukaturki/slider-light/ | O54: В особенностях: λ0,2 Вт/(м·К), нагрузка на конструкции ниже до 2х раз; плитка с гранью не более 45 см. Расхождение по воде: в характеристиках 0,29–0,33 л на 1 кг, в разделе работ 0,28–0,3 л (8,4–9,0 л на мешок 30 кг). Полного наименования на странице нет. Декларация РОСС RU (кода товара в имени нет) не включена.
A55: Perel | B55: Штукатурки цементные и цементно-известковые (вкл. обрызг) | C55: да | D55: Perel Robust | E55: Perel Robust, 25 кг, цементная штукатурка для ручного нанесения | F55: 1 | G55: Штукатурная смесь на основе цементно-известкового вяжущего для выравнивания стен из бетона, кирпича, газобетона, а также заделки стыков и отдельных неровностей бетонных и железобетонных плит для внутренних и наружных работ, в сухих и влажных помещениях. | H55: Бумажные крафт-мешки по 25 кг. | I55: 15-16 кг/м² при толщине слоя 10 мм. | L55: — | N55: https://td-perel.ru/catalog/tsementnaya-shtukaturka/tsementno-izvestkovaya-shtukaturka-perel-robust-25-kg/ | O55: В блоке характеристик только артикул. Ручное нанесение; машинная версия — Robust-M 0514 (отдельный товар в этой пачке). Многослойно — каждый слой через ~24 ч; для фасадов сетка 20х20/40х40 мм.
A56: Perel | B56: Штукатурки цементные и цементно-известковые (вкл. обрызг) | C56: да | D56: Perel Robust-M | E56: Perel Robust-M, 25 кг, цементная штукатурка для машинного нанесения | F56: 1 | G56: Штукатурная смесь на основе цементно-известкового вяжущего для выравнивания стен из бетона, кирпича, газобетона, а также заделки стыков и отдельных неровностей бетонных и железобетонных плит для внутренних и наружных работ, в сухих и влажных помещениях. | H56: Бумажные крафт-мешки по 25 кг. | I56: 15-16 кг/м2 при толщине слоя 10 мм. | L56: — | N56: https://td-perel.ru/catalog/tsementnaya-shtukaturka/tsementno-izvestkovaya-shtukaturka-perel-robust-m-25-kg/ | O56: В блоке характеристик только артикул. Для машинного (и ручного) нанесения; текст почти совпадает с Robust 0515.
A57: Perel | B57: Штукатурки цементные и цементно-известковые (вкл. обрызг) | C57: да | D57: Perel TeploRob | E57: Perel TeploRob, 20 кг, легкая цементная штукатурка с перлитом | F57: 1 | G57: Лёгкая штукатурная смесь на основе цементно-известкового вяжущего и легкого минерального наполнителя (перлита) для выравнивания стен из бетона, кирпича, газобетона, а также заделки стыков и отдельных неровностей бетонных и железобетонных плит в сухих, влажных помещениях и для наружных работ. | H57: Бумажные крафт-мешки по 20 кг. | I57: 11-12 кг/м² при толщине слоя 10 мм. | L57: — | N57: https://td-perel.ru/catalog/tsementnaya-shtukaturka/tsementno-izvestkovaya-shtukaturka-perel-teplorob-20-kg/ | O57: В блоке характеристик только артикул. Для ручного нанесения. Отдельный артикул от TeploRob TR 0517 (35 кг) — разные продукты, series_key разведены.
A58: Perel | B58: Штукатурки цементные и цементно-известковые (вкл. обрызг) | C58: да | D58: Perel TeploRob TR | E58: Perel TeploRob TR, 35 кг, облегченная цементная штукатурка с перлитом | F58: 1 | G58: Облегченная штукатурная смесь на основе цементно-известкового вяжущего и легкого минерального наполнителя (перлита) для выравнивания стен из бетона, кирпича, газобетона, а также заделки стыков и отдельных неровностей бетонных и железобетонных плит в сухих, влажных помещениях и для наружных работ. | H58: Бумажные крафт-мешки по 35 кг. | I58: 12-13 кг/м² при толщине слоя 10 мм. | K58: ГОСТ 31357-2007 «Смеси сухие строительные на цементном вяжущем. Общие технические условия» | L58: — | N58: https://td-perel.ru/catalog/tsementnaya-shtukaturka/oblegchennaya-tsementno-izvestkovaya-shtukaturka-perel-teplorob-tr-35-kg/ | O58: В блоке характеристик только артикул. Отличается от TeploRob 0518 (20 кг): облегчённая, 35 кг, вода 6,5-7,5 л на мешок, расход 12-13 кг/м². Подрезка через 6–24 ч, увлажнять 2–5 суток. Единственная карточка пачки со ссылкой на ГОСТ.
A59: Основит | B59: Штукатурки цементные и цементно-известковые (вкл. обрызг) | C59: да | D59: Основит PRO Штукатурка цементная | E59: Штукатурка цементная Основит PRO | F59: 1 | G59: Штукатурка Фасадная ОСНОВИТ PRO предназначена для выравнивания стен из кирпича, бетона и ячеистого бетона. | H59: 25 кг | I59: 16-17 кг/м² | J59: 5-30 мм | K59: КП III, F50 механизированного нанесения, ГОСТ 33083-2014 | L59: — | N59: https://osnovit.ru/catalog/osnovit-pro/shtukaturka-fasadnaya-pro/ | O59: В тексте назначения продукт назван «Штукатурка Фасадная ОСНОВИТ PRO», адрес …/shtukaturka-fasadnaya-pro/, заголовок — «Штукатурка цементная». Выравнивающая цементная штукатурка (для фасадов выше цоколя и помещений), поэтому plaster_cement, а не plaster_facade_base. base_quote взят из названия (в тексте вяжущее отдельно не названо). Нет pdf во входе.
A60: Основит | B60: Штукатурки цементные и цементно-известковые (вкл. обрызг) | C60: да | D60: Основит Стартвэлл PC211 M | E60: Штукатурка цементная Основит Стартвэлл PC211 M 25 кг | F60: 1 | G60: ОСНОВИТ СТАРТВЭЛЛ PC211 M — цементная штукатурка для базового выравнивания стен внутри и снаружи зданий. | H60: 25 кг | I60: 13-14 кг/м | J60: 5-30 мм | K60: КП III, F50, механизированного нанесения. Соответствует ГОСТ 33083-2014 | L60: — | N60: https://osnovit.ru/catalog/shtukaturki-tsementnye/osnovit-startvell-pc211-m-shtukaturka-tsementnaya/ | O60: Расход при слое 10 мм указан как «13-14 кг/м» (без квадрата — так на странице). В первой строке марка морозостойкости F50, а в характеристиках и преимуществах — 75 циклов. Техкарты в документации нет.
A61: Основит | B61: Штукатурки цементные и цементно-известковые (вкл. обрызг) | C61: да | D61: Основит Стартвэлл PC22 H | E61: Штукатурка цементная высокопрочная Основит Стартвэлл PC22 H 25 кг | F61: 1 | G61: ОСНОВИТ СТАРТВЭЛЛ PC22 H — высокопрочная цементная штукатурка для выравнивания стен и поверхностей, подвергающихся повышенным эксплуатационным нагрузкам. | H61: 25 кг | I61: 16 кг/м² | J61: 5–30 мм | K61: КП IV, F100. Соответствует ГОСТ 33083-2014 | L61: — | N61: https://osnovit.ru/catalog/shtukaturki/osnovit-bigvell-t-22-shtukaturka-fasadnaya-profi/ | O61: Адрес карточки osnovit-bigvell-t-22-… (старое имя «Бигвэлл Т-22»), заголовок — Стартвэлл PC22 H. Противоречия на странице: первая строка «для наружных работ, КП IV, F100», а преимущество «Для внутренних и наружных работ» и морозостойкость в характеристиках 75 циклов. Расход воды дан отдельно для производственных кластеров ПБЕ Коломна (К), Бердск (С), Невинномысск (Н), Ульяновск (У). Расход при сло
A62: Основит | B62: Штукатурки цементные и цементно-известковые (вкл. обрызг) | C62: да | D62: Основит Техно PC20 M | E62: Обрызг штукатурный Основит Техно PC20 M 25 кг | F62: 1 | G62: ОСНОВИТ ТЕХНО PC20 M — цементный штукатурный обрызг для предварительной подготовки бетонных, кирпичных и других минеральных оснований перед нанесением выравнивающей штукатурки. | H62: 25 кг | I62: 1,6 кг/м² | J62: 4-12 мм | K62: КП IV, F50, механизированного нанесения. Соответствует ГОСТ 33083-2014. | L62: есть | M62: Красный | N62: https://osnovit.ru/catalog/shtukaturki/tekhno-pc20-m-shtukaturnyy-obryzg-osnovit/ | O62: Зимняя версия по тексту — «ОСНОВИТ ТЕХНО PC20/2 MF» (до −10 °C), другой код; техкарта зимней версии упомянута без ссылки. Цвет «Красный» — необычно для обрызга, стоит перепроверить.
A63: Основит | B63: Штукатурки цементные и цементно-известковые (вкл. обрызг) | C63: да | D63: Основит Техно PC21 M | E63: Штукатурка цементная фасадная Основит Техно PC21 M 30 кг | F63: 1 | G63: ОСНОВИТ ТЕХНО PC21 M — цементная штукатурка для выравнивания стен из бетона, кирпича, пено- и газобетона. | H63: 30 кг | I63: 13 кг/м2 | J63: 5-30 мм | K63: ГОСТ 33083-2014 | L63: есть | M63: серый | N63: https://osnovit.ru/catalog/shtukaturki/startvell-pc-21-m-shtukaturka-fasadnaya-osnovit-/ | O63: Зимняя версия по тексту — «ОСНОВИТ ТЕХНО PC21/2 MF» (до −10 °C), другой код. URL «startvell-pc-21-m» — след прежнего имени (Стартвэлл). Противоречие сроков: «Срок хранения в бумажном мешке 12 месяцев» и «18 мес. (в бумажном мешке)». Референц-объекты: Открытие Арена, ЖК «Парковые Аллеи» и др.
A64: Основит | B64: Штукатурки цементные и цементно-известковые (вкл. обрызг) | C64: да | D64: Основит Техно PC23 M | E64: Штукатурка шпаклевка цементная Основит Техно PC23 M | F64: 1 | G64: ОСНОВИТ ТЕХНО PC23 M — цементная штукатурка-шпаклевка для выравнивания стен из бетона, пено- и газобетона, а также поверхностей, ранее выровненных цементными составами. | H64: 25 кг/30 кг | I64: 12 кг/м² | J64: слоем от 1 до 30 мм | K64: КП II, F50, механизированного нанесения. Соответствует ГОСТ 33083-2014 | L64: — | N64: https://osnovit.ru/catalog/shtukaturki/tekhno-pc23-m/ | O64: Комбинированный продукт «штукатурка-шпаклевка» — отнесён к plaster_cement (можно и putty_cement). Раздел производителя — «Серия ТЕХНО». Вес упаковки «25 кг/30 кг» — две фасовки. Расход дан при слое 10 мм.
A65: Основит | B65: Штукатурки цементные и цементно-известковые (вкл. обрызг) | C65: да | D65: Основит Техно PC24/1 ML | E65: Штукатурка цементная Основит Техно PC24/1 ML 25 кг | F65: 1 | G65: ОСНОВИТ ТЕХНО PC24/1 ML — легкая цементная штукатурка на основе перлита для выравнивания стен из бетона, кирпича, пено- и газобетона. | H65: 25 кг | I65: 10-11 кг/м² | J65: 10-30 мм | K65: ГОСТ 33083-2014 | L65: — | M65: серый | N65: https://osnovit.ru/catalog/seria-techno/tsementnaya-shtukaturka-osnovit-tekhno-pc24-1-ml/ | O65: Лёгкая штукатурка на перлите; КП II, F50; заявлены тепло- и звукоизоляционные свойства. Температура эксплуатации -40…+60 °С.
A66: Dauer | B66: Шпаклёвки гипсовые | C66: да | D66: Dauer FINNER 43 | E66: Dauer FINNER® 43W Шпатлевка гипсовая универсальная белая | F66: 1 | G66: Внутри сухих отапливаемых помещений для толстослойного и финишного выравнивания (слой от 1 до 20 мм) поверхности стен и потолков под дальнейшую отделку обоями и нанесения финишных декоративных покрытий; для заделки трещин, выбоин, раковин слоем до 20 мм, для заполнения швов ГВЛ, ГКЛ с обязательным применением армирующей ленты. | H66: 20 кг. | I66: 0,9 кг/м² | J66: слой от 1 до 20 мм | K66: ГОСТ Р 58278-2018 | L66: — | N66: https://dauer.ru/catalog/shpatlevki/finner-43/ | O66: Расход 0,9 кг/м² указан на слой 1 мм. В описании слой 1–20 мм, в характеристиках рекомендуемый 1–15 мм и локально 20 мм. Полное наименование «Dauer Finner Между (Inter) 43 W». Документ подписан «Шпатлевка гипсовая выравнивающая белая», в h1 — «универсальная».
A67: Perel | B67: Шпаклёвки гипсовые | C67: да | D67: Perel Plaster Wall | E67: Perel Plaster Wall, белая, 25 кг, шпаклевка гипсовая | F67: 1 | G67: Универсальная гипсовая шпаклевка для внутренних работ на основе природного гипса и европейских полимерных добавок для заделки стыков листов ГКЛ и ГВЛ и первичного выравнивания стен и потолков перед финишной отделкой. | H67: Бумажные крафт-мешки по 25 кг. | J67: слоя шпатлевки толщиной 1-2 мм | L67: — | N67: https://td-perel.ru/catalog/gipsovaya_shpaklevka/shpaklevka-gipsovaya-perel-plaster-wall-belaya-25-kg/ | O67: В лиде шпаклёвка названа «атмосферостойкая», хотя назначение — только внутренние работы в сухих помещениях. Расход не указан. Толщина 1-2 мм дана в контексте времени высыхания, рекомендованного слоя нет. Срок хранения 6 месяцев.
A68: Основит | B68: Шпаклёвки гипсовые | C68: да | D68: Основит Версилк PG34 W | E68: Шпаклевка гипсовая универсальная белая Основит Версилк PG34 W 20 кг | F68: 1 | G68: Шпаклевка ОСНОВИТ ВЕРСИЛК PG34 W предназначена для заделки швов и стыков ГКЛ и ГВЛ, для выравнивания ГКЛ, ГВЛ, ПГП и СМЛ, а также для финишного выравнивания стен и потолков в сухих помещениях. | H68: 20 кг | I68: 0,8-0,9 кг/м² | J68: 1-10 мм | L68: — | N68: https://osnovit.ru/catalog/shpaklevki/shpaklevka-gipsovaya-vyravnivayushchaya-belaya-versilk-pg-34-w/ | O68: В отличие от соседних гипсовых шпаклёвок, строки «Смесь сухая … ГОСТ Р 58278» нет — ГОСТ не указан; сухая смесь следует из «Расход воды на 1 кг сухой смеси». Расход при слое 1 мм, при заделке швов — 0,26 кг/м². В преимуществах опечатка «ГЛК» (вместо ГКЛ), так на странице.
A69: Основит | B69: Шпаклёвки гипсовые | C69: да | D69: Основит Шовсилк PG33 H | E69: Шпаклевка гипсовая высокопрочная для швов и стыков белая Основит Шовсилк PG33 H 20 кг | F69: 1 | G69: предназначена для заделки стыков, швов и возможных повреждений ГКЛ, ГВЛ, ПГП и СМЛ. Заделку стыковочных швов листов с полукруглой утонённой кромкой (ПЛУК) возможно производить без использования армирующих шовных лент. | H69: 20 кг | I69: 0,8-0,9 кг/м² | J69: до 10 мм | K69: ГОСТ Р 58278-2018 | L69: — | N69: https://osnovit.ru/catalog/shpaklevki/shovsilk-pg33-h-shpaklyevka-gipsovaya-vysokoprochnaya-osnovit/ | O69: Расход дан при слое 1 мм. Прямой фразы «для внутренних работ» нет — только «Для помещений с нормальной влажностью». В тексте код набран с кириллической «Н» («PG33 Н»), в заголовке — латиница.
A70: Основит | B70: Шпаклёвки гипсовые | C70: да | D70: Основит Эконсилк PG35 W | E70: Шпаклевка гипсовая финишная белая Основит Эконсилк PG35 W | F70: 1 | G70: Шпаклевка ОСНОВИТ ЭКОНСИЛК PG35 W предназначена для выравнивания стен и потолков, для заделки швов ГКЛ и ГВЛ. | H70: 5, 10, 20 кг | I70: 0,8-0,9 кг/м² | J70: 0,1-5 мм | K70: ГОСТ Р 58278-2024 | L70: — | N70: https://osnovit.ru/catalog/shpaklevki/ekonsilk-pg35-w/ | O70: Расход при слое 1 мм. ГОСТ Р 58278-2024 (у PG33 H и PG36 W — редакция 2018). Срок хранения разный для бумажного (6 мес.) и пластикового (12 мес.) мешка.
A71: Основит | B71: Шпаклёвки гипсовые | C71: да | D71: Основит Элисилк PG36 W | E71: Шпаклевка гипсовая суперфинишная белая Основит Элисилк PG36 W | F71: 1 | G71: Шпаклевка ОСНОВИТ ЭЛИСИЛК PG36 W предназначена для окончательного выравнивания стен и потолков, для заделки швов ГКЛ и ГВЛ. | H71: 5, 20 кг | I71: 0,8-0,9 кг/м² | J71: 0-4 мм | K71: ГОСТ Р 58278-2018 | L71: — | N71: https://osnovit.ru/catalog/shpaklevki/elisilk-t-36-belaya/ | O71: Расход при слое 1 мм. Две фасовки (5 и 20 кг). Адрес карточки elisilk-t-36-belaya (старое имя «Т-36»).
A72: Dauer | B72: Шпаклёвки цементные | C72: да | D72: Dauer FINNER 40 | E72: Dauer FINNER® 40W Шпатлевка цементная армированная базовая белая | F72: 2 | G72: Для толстослойного и финишного выравнивания (слой от 1 до 15 мм) поверхности фасадов, стен и потолков внутри всех видов жилых и нежилых помещений, в т.ч. влажных и неотапливаемых: подвалы, балконы и лоджии, паркинги, лестничные пролеты, марши, склады, душевые и ванные комнаты. | H72: 25 кг. | I72: 0,9 кг/м2 | J72: 1 - 15 мм | K72: ГОСТ 33699-2015 | L72: есть | N72: https://dauer.ru/catalog/shpatlevki/finner-exter-40w-shpatlevka-tsementnaya-armirovannaya-bazovaya-belaya/ | O72: Полное наименование «Dauer Finner Экстерьер (Exter) 40 W». Белый вариант FINNER 40 (см. 40G), характеристики совпадают. Есть зимняя версия. Расход 0,9 кг/м2 при слое 1 мм.
A73: Dauer | B73: Шпаклёвки цементные | C73: да | D73: Dauer FINNER 41 | E73: Dauer FINNER® 41G Шпатлевка цементная финишная серая | F73: 2 | G73: Для финишного выравнивания (слой от 0,2 до 5 мм) поверхности фасадов, стен и потолков, внутри всех видов помещений, в т.ч. влажных и неотапливаемых: подвалы, лоджии, балконы, паркинги, лестничные пролеты, марши, склады, душевые и ванные комнаты. Используется для выравнивания поверхности под нанесение финишных декоративных покрытий и многослойное окрашивание ЛКМ. | H73: 20 кг. | I73: 0,9 кг/м2 | J73: 0,2 - 5 мм | K73: ГОСТ 33699-2015 | L73: — | N73: https://dauer.ru/catalog/shpatlevki/finner-exter-41g-shpatlevka-tsementnaya-finishnaya-seraya/ | O73: Полное наименование «Dauer Finner Экстерьер (Exter) 41 G». Финишная, слой 0,2–5 мм, срок годности не менее 9 месяцев; зимняя версия не упомянута. В списке линейки на странице есть FINNER 41W (белая финишная) и 43W (гипсовая) — не в этой пачке; 41W при появлении — тот же series_key «Dauer FINNER 41».
A74: Perel | B74: Шпаклёвки цементные | C74: да | D74: Perel FACADE-B | E74: Perel FACADE-B, белая, 20 кг, шпатлевка цементная | F74: 1 | G74: Атмосферостойкая шпатлевка на основе белого цемента, микромрамора и европейских полимерных добавок для финишной отделки стен и потолков перед высококачественной покраской фасадов и влажных помещений зданий. | H74: Бумажные крафт-мешки по 25 кг. | I74: 0,9-1,1 кг на м2 поверхности при толщине слоя 1 мм. | L74: — | M74: белая | N74: https://td-perel.ru/catalog/tsementnaya_shpaklevka/shpatlevka-tsementnaya-perel-facade-b-belaya-20-kg/ | O74: РАСХОЖДЕНИЕ ФАСОВКИ: в названии «20 кг», в упаковке «Бумажные крафт-мешки по 25 кг» и вода «на 25 кг сухой смеси». В блоке характеристик только артикул.
A75: Perel | B75: Шпаклёвки цементные | C75: да | D75: Perel FACADE-C | E75: Perel FACADE-C, серая, 25 кг, шпатлевка цементная | F75: 1 | G75: Ремонтная шпатлевочная смесь на основе цемента, мытого белого песка и европейских полимерных добавок, для заделки раковин и трещин стен и потолков перед финишной отделкой фасадов и помещений с любой влажностью. | H75: Бумажные крафт-мешки по 25 кг. | I75: 1,5-1,7 кг/м2 поверхности при толщине слоя 1 мм. | L75: — | M75: серая | N75: https://td-perel.ru/catalog/tsementnaya_shpaklevka/shpatlevka-tsementnaya-facade-c-seraya-25-kg/ | O75: Короткое описание — «для финишной отделки», полное — «ремонтная… для заделки раковин и трещин» (базовая/ремонтная, не финишная). Время высыхания слоя 6 мм ~2-3 суток. В блоке характеристик только артикул. FACADE-B и FACADE-C — разные продукты (разный состав), series_key разведены.
A76: Основит | B76: Шпаклёвки цементные | C76: да | D76: Основит Базсилк PC30 | E76: Шпаклевка цементная фасадная универсальная белая Основит Базсилк PC30 MW 20 кг | F76: 2 | G76: Шпаклевка ОСНОВИТ БАЗСИЛК PC30 MW предназначена для выравнивания стен и потолков в сухих и влажных помещениях, фасадов, цоколей. | H76: 20 кг | I76: 1,2 кг/м² | J76: 1-10 мм | K76: 180/10, ГОСТ 33699-2015 | L76: — | N76: https://osnovit.ru/catalog/shpaklevki/bazsilk-t-30/ | O76: Пара по цвету с Базсилк PC30 MG (серая) — один series_key. Расход при слое 1 мм. Есть ещё карточка «БАЗСИЛК PC30 MW (Н)» с расходящимися характеристиками (см. отдельную запись).
A77: Основит | B77: Шпаклёвки цементные | C77: да | D77: Основит Белсилк PC32 W | E77: Шпаклевка цементная финишная белая Основит Белсилк PC32 W | F77: 1 | G77: предназначена для финишного выравнивания фасадов зданий, стен и потолков в сухих и влажных помещениях. | H77: 5, 20 кг | I77: 1,2 кг/м² | J77: 0-4 мм | K77: 180/10, ГОСТ 33699-2015 | L77: — | N77: https://osnovit.ru/catalog/shpaklevki/belsilk-t-32/ | O77: Финишная белая цементная; серый аналог — Грейсилк PC31 G (другое имя и код, отдельный series_key). В тексте код «РС32» кириллицей. Расход при слое 1 мм.
A78: Основит | B78: Шпаклёвки цементные | C78: да | D78: Основит Грейсилк PC31 G | E78: Шпаклевка цементная финишная серая Основит Грейсилк PC31 G 20 кг | F78: 1 | G78: предназначена для финишного выравнивания фасадов, стен и потолков в сухих и влажных помещениях. | H78: 20 кг | I78: 1,3 кг/м² | J78: 0-4 мм | K78: 180/6, ГОСТ 33699-2015 | L78: — | N78: https://osnovit.ru/catalog/shpaklevki/greysilk-t-31/ | O78: Финишная серая цементная, марка 180/6 (у Белсилк PC32 W — 180/10). В тексте код «РС31» кириллицей. Расход при слое 1 мм.
A79: Perel | B79: Шпаклёвки полимерные (сухие) | C79: да | D79: Perel FINISH | E79: Perel FINISH, супербелая, 20 кг, шпатлевка полимерная финишная | F79: 1 | G79: Супербелая, трещиноустойчивая полимерная шпатлевка для финишной отделки стен и потолков. Для внутренних работ в сухих помещениях. | H79: Бумажные крафт-мешки по 20 кг. | I79: 1,1-1,2 кг/м² поверхности при толщине слоя 1 мм. | L79: — | N79: https://td-perel.ru/catalog/polimernaya_shpaklevka/shpatlevka-polimernaya-finishnaya-perel-finish-superbelaya-20-kg/ | O79: Блок характеристик содержит только артикул; толщина слоя, ГОСТ, прочность/адгезия не указаны. В названии «шпатлевка», в разделе каталога «Полимерная шпаклевка».
A80: Основит | B80: Шпаклёвки полимерные (сухие) | C80: да | D80: Основит Эконсилк PP38 W | E80: Шпаклевка полимерная финишная супербелая Основит Эконсилк PP38 W | F80: 1 | G80: Шпаклевка ОСНОВИТ Эконсилк PP38 W предназначена для выравнивания стен и потолков в сухих и влажных помещениях. | H80: 5, 20 кг | I80: 1,1 кг/м² | J80: 0,5-5 мм | L80: — | N80: https://osnovit.ru/catalog/shpaklevki/ekonsilk-PP-38-W/ | O80: Сухая полимерная, ГОСТ не указан. В составе натуральный мрамор, жизнеспособность 24 часа. Расход при слое 1 мм.
A81: Основит | B81: Шпаклёвки полимерные (сухие) | C81: да | D81: Основит Элисилк PP37 W | E81: Шпаклевка полимерная суперфинишная супербелая Основит Элисилк PP37 W 20 кг | F81: 1 | G81: Шпаклевка ОСНОВИТ ЭЛИСИЛК PP37 W предназначена для окончательного выравнивания стен и потолков в сухих и влажных помещениях. | H81: 20 кг | I81: 1 кг/м² | J81: 0-2 мм | L81: — | N81: https://osnovit.ru/catalog/shpaklevki/elisilk-PP37/ | O81: Сухая полимерная (мешок; есть «Расход воды на 1 кг сухой смеси», хранение в бумажном/пластиковом мешке). ГОСТ не указан. В составе натуральный мрамор, жизнеспособность 24 часа. Расход при слое 1 мм.
A82: Dauer | B82: Плиточные клеи | C82: да | D82: Dauer CONECTOR 02 | E82: Dauer CONECTOR® 02 Клей Оптимум C0 Т | F82: 1 | G82: Для укладки на пол и стены керамической плитки по ГОСТ 13996 (со средним и высоким водопоглощением) и других облицовочных материалов с водопоглощением не менее 5%. Применяется внутри помещений с любым уровнем влажности. | H82: 25 кг. | I82: 1,3 – 1,4 кг/м² | J82: 2 – 8 мм | K82: ГОСТ Р 56387 | L82: есть | N82: https://dauer.ru/catalog/plitochnye-klei/conector-02/ | O82: Класс — только в названии: «C0 Т». Полное наименование «Dauer Conector Дом (Home) 02». Только внутренние работы. Есть зимняя версия. Таблицы расхода по зубцу нет — только расход 1,3 – 1,4 кг/м² на 1 мм слоя.
A83: Dauer | B83: Плиточные клеи | C83: да | D83: Dauer CONECTOR 14 | E83: Dauer CONECTOR® 14 Клей Армированный С1 TЕ | F83: 1 | G83: Для выполнения работ по облицовке фасадов выше цокольной части и помещений с любым уровнем влажности. Применяется для укладки керамической плитки, керамогранита и натурального камня весом до 150 кг/м2. | H83: 25 кг. | I83: 1,3 – 1,4 кг/м² | J83: 2 – 15 мм | K83: ГОСТ Р 56387 | L83: есть | N83: https://dauer.ru/catalog/plitochnye-klei/conector-14/ | O83: Класс — только в названии: «С1 TЕ» (армированный). Полное наименование «Dauer Conector Следующий (Next) 14 Фасад (Fasad)». Таблица расхода по зубцу: до 120 мм / 4 мм — 2,6 кг/м2; до 330 мм / 6 мм — 3,9; до 450 мм / 8 мм — 5,2; до 600 мм / 10 мм — 6,5. Странность: прочность после водной среды, высоких температур и замораживания помечена «не более 0,5 МПа» (по смыслу «не менее»). Есть зимняя версия
A84: Dauer | B84: Плиточные клеи | C84: да | D84: Dauer CONECTOR 22 | E84: Dauer CONECTOR® 22 Клей высокоэффективный С2 T | F84: 1 | G84: Для наружных и внутренних облицовочных работ фасадов зданий и сооружений (включая цокольную часть) крупноформатными облицовочными материалами (керамическая и клинкерная плитка, натуральный камень и керамогранит). | H84: 25 кг. | I84: 1,3 – 1,4 кг/м² | J84: 2 – 20 мм | K84: ГОСТ Р 56387 | L84: есть | N84: https://dauer.ru/catalog/plitochnye-klei/conector-force-22-kley-vysokoeffektivnyy-s2-t-gost-r-56387/ | O84: Класс — только в названии: «С2 T». Полное наименование «Dauer Conector Сила (Force) 22». Таблица расхода по зубцу: до 330 мм / 4 мм — 2,6 кг/м2; до 450 / 6 — 3,9; до 600 / 8 — 5,2; до 1200 / 10 — 6,5. Есть зимняя версия. Может применяться для монтажа теплоизоляционных плит. Жизнеспособность записана «4 часов».
A85: Dauer | B85: Плиточные клеи | C85: да | D85: Dauer CONECTOR 22 Макс | E85: Dauer CONECTOR® 22 Макс Клей Армированный С2 TЕ | F85: 1 | G85: Для наружных и внутренних облицовочных работ фасадов зданий и сооружений (включая цокольную часть) крупноформатными облицовочными материалами (керамическая и клинкерная плитка, натуральный камень и керамогранит). | H85: 25 кг. | I85: 1,3 – 1,4 кг/м² | J85: 2 – 20 мм | K85: ГОСТ Р 56387 | L85: — | N85: https://dauer.ru/catalog/plitochnye-klei/conector-22-max/ | O85: Класс — только в названии: «С2 TЕ». Полное наименование «Dauer Conector Сила (Force) 22 Макс (Max)». Отдельный продукт от CONECTOR 22 (жизнеспособность 7 часов, открытое время 30 минут, «Максимально эффективен при облицовке больших площадей»). Зимняя версия на странице не упомянута. Таблица расхода по зубцу — как у CONECTOR 22 (2,6 / 3,9 / 5,2 / 6,5 кг/м2).
A86: Dauer | B86: Плиточные клеи | C86: да | D86: Dauer CONECTOR Плюс | E86: Dauer CONECTOR® Плюс Клей Универсальный C1 T | F86: 1 | G86: Для укладки на пол и стены керамической и клинкерной плитки, керамогранита и натурального камня (кроме мрамора, базальта, габбро) весом до 80 кг/м². | H86: 25/40 кг. | I86: 1,3 – 1,4 кг/м² | J86: 2 – 15 мм | K86: ГОСТ Р 56387 | L86: есть | N86: https://dauer.ru/catalog/plitochnye-klei/conector-home-plus-kley-universalnyy-c1-gost-r-56387-2018/ | O86: Класс — только в названии: «C1 T». Полное наименование «Dauer Conector Дом (Home) Плюс (Plus)». Фасовка 25 и 40 кг. Таблица расхода по зубцу: до 15 см / 4 мм — 2,4 кг/м2; до 30 см / 6 мм — 3,6; до 45 см / 8 мм — 4,8; до 60 см / 10 мм — 6,0. Максимальная грань керамогранита 60 см. Есть зимняя версия.
A87: Perel | B87: Плиточные клеи | C87: да | D87: Perel BASIS C0 | E87: Perel BASIS C0, 25 кг, клеевая смесь | F87: 1 | G87: Клеевая смесь Perel Basis C0 на основе цемента с добавлением химических добавок для укладки на пол и стены всех видов керамической плитки. | H87: Бумажные крафт-мешки 25 кг. | I87: 3,5-5,0 кг смеси на м2 при использовании зубчатого шпателя 6×6 мм. | J87: слоем 3-5 мм | K87: C0 | L87: — | N87: https://td-perel.ru/catalog/klei-dlya-plitki-i-kamnya/kleevaya-smes-perel-basis-c0-25-kg/ | O87: РАСХОЖДЕНИЕ: в лиде «Для наружных и внутренних работ», в описании «Для внутренних работ.» Класс C0 есть только в названии, ГОСТ не указан. Жизнеспособность 90 минут. В «Характеристиках» только артикул.
A88: Perel | B88: Плиточные клеи | C88: да | D88: Perel Keramogranit C1T | E88: Perel Keramogranit C1T, 25 кг, клеевая смесь | F88: 1 | G88: Усиленный плиточный клей на цементной основе с использованием европейских полимерных и армирующих добавок для укладки плит из керамогранита, мрамора, композитного камня по любым недеформируемым поверхностям в сухих и влажных помещениях, жилых, общественных, производственных и иных зданиях. | H88: Бумажные крафт-мешки по 25 кг. | I88: 3,5-5,0 кг смеси на м2 при использовании зубчатого шпателя 6×6 мм. | J88: слоем 3-5 мм | K88: C1T | L88: — | N88: https://td-perel.ru/catalog/klei-dlya-plitki-i-kamnya/kleevaya-smes-perel-keramogranit-c1t-25-kg/ | O88: Класс C1T есть только в названии, ГОСТ не указан. Жизнеспособность 180 минут. Есть раздел «Видеообзоры» (только заголовок). В «Характеристиках» только артикул.
A89: Perel | B89: Плиточные клеи | C89: да | D89: Perel Premium C1TE | E89: Perel Premium C1TE, 25 кг, клеевая смесь беспылевая | F89: 1 | G89: Используется для укладки тяжелой плитки больших размеров, натурального и искусственного камня, клинкерной плитки на минеральные недеформирующиеся основания в сухих и влажных помещениях. | H89: Бумажные крафт-мешки 25 кг. | I89: 3,5-4,0 кг смеси на м2 при использовании зубчатого шпателя 6×6 мм. | J89: 3-15 мм | K89: Класс по ГОСТ 56387 - 2018 | L89: есть | N89: https://td-perel.ru/catalog/klei-dlya-plitki-i-kamnya/kleevaya-smes-perel-premium-c1te-25-kg/ | O89: Беспылевая. Модификация «зима» упомянута в инструкции без отдельного артикула. РАСХОЖДЕНИЯ внутри карточки: расход в тексте 3,5-4,0 кг/м², в характеристиках 3,5-5 кг/м²; жизнеспособность в тексте 90 минут, в характеристиках не менее 180 мин. ГОСТ записан без «Р» («ГОСТ 56387 - 2018»). Пригодна для тёплых полов, бассейнов и чаш фонтанов.
A90: Perel | B90: Плиточные клеи | C90: да | D90: Perel Supremium | E90: Perel Supremium С2 ТЕ S1, 25 кг, эластичная, водостойкая, беспылевая клеевая смесь | F90: 1 | G90: Используется для укладки тяжелой плитки больших размеров, натурального и искусственного камня, клинкерной плитки на минеральные недеформирующиеся основания в сухих и влажных помещениях. | H90: Бумажные крафт-мешки - 25 кг . | I90: 3,5-5,0 кг смеси на м2 при использовании зубчатого шпателя 6×6 мм. | J90: 3-10 мм | K90: Смесь сухая клеевая на цементном вяжущем С2 ТЕ S1, ГОСТ 56387 - 2018. | L90: есть | N90: https://td-perel.ru/catalog/klei-dlya-plitki-i-kamnya/perel-supremium/ | O90: Эластичная, водостойкая, беспылевая. На одной карточке две модификации: «Артикул 031 5 – «лето»» (от +5 до +30) и «Артикул 531 5 – «зима»» (от -5 до +10); артикулы записаны с пробелом. Класс в названии набран кириллицей «С2 ТЕ S1», в характеристиках — вперемешку кириллицей и латиницей «С2 TЕ S1»; ГОСТ без «Р». В характеристиках 17 пар, не вошли 3: прочность после высоких температур (1,0 МПа), удер
A91: Perel | B91: Плиточные клеи | C91: да | D91: Perel White C1TE | E91: Perel White C1TE, 25 кг, белая клеевая смесь | F91: 1 | G91: Клеевая смесь «White» на основе супер-белого цемента, отмытых кварцевых песков и европейских полимерных добавок для укладки всех видов керамической плитки, мрамора, натурального или искусственного камня по любым недеформируемым поверхностям в сухих и влажных помещениях, жилых, общественных, производственных и иных зданиях. | H91: Бумажные крафт-мешки 25 кг. | I91: 3,5-4,0 кг смеси на м2 при использовании зубчатого шпателя 6×6 мм. | J91: слоем 3-5 мм | K91: C1TE | L91: — | N91: https://td-perel.ru/catalog/klei-dlya-plitki-i-kamnya/kleevaya-smes-perel-white-c1te-25-kg/ | O91: Класс C1TE есть только в названии, ГОСТ не указан. Жизнеспособность 90 минут. Есть раздел «Видеообзоры» (только заголовок). В «Характеристиках» только артикул.
A92: Основит | B92: Плиточные клеи | C92: да | D92: Основит PRO Плиточный клей стандарт | E92: Плиточный клей стандарт Основит PRO | F92: 1 | G92: Плиточный клей стандарт ОСНОВИТ PRO предназначен для облицовки стен и пола керамической плиткой, а также укладки напольных плит из керамогранита. | H92: 25 кг | J92: 2-8 мм | K92: C0T, ГОСТ Р 56387-2018 | L92: — | N92: https://osnovit.ru/catalog/osnovit-pro/plitochnyy-kley-standart-pro/ | O92: Расход только таблицей по размеру плитки (зуб 4 мм → 2,1 кг/м² … зуб 10 мм → 5,2 кг/м²), отдельной строки расхода нет — consumption_quote пуст. Расхождение: в преимуществах «Время корректировки плитки 15 минут», в характеристиках «10 минут». Опечатка на странице: цвет «с ерый». Нет pdf во входе.
A93: Основит | B93: Плиточные клеи | C93: да | D93: Основит PRO плиточный клей усиленный | E93: Плиточный клей усиленный Основит PRO | F93: 1 | G93: Плиточный клей усиленный ОСНОВИТ PRO предназначен для облицовки стен и полов керамической плиткой, керамогранитом, натуральным и искусственным камнем (вес до 600 г/100 см²). | H93: 25 кг | I93: 1,3-1,5 кг/м² | J93: 2-15 мм | K93: C1, ГОСТ Р 56387-2018 | L93: — | M93: серый | N93: https://osnovit.ru/catalog/plitochnye-klei/plitochnyy-kley-usilennyy-pro/ | O93: Линейка «Основит PRO» (отдельный раздел каталога), кода модели нет. «В первые 10 минут приклеивания материалов обладает повышенной силой сцепления».
A94: Основит | B94: Плиточные клеи | C94: да | D94: Основит Базпликс AC10 | E94: Клей плиточный Основит Базпликс AC10 [C0T] 25 кг | F94: 1 | G94: Плиточный клей Основит Базпликс AC10 предназначен для облицовки стен и пола керамической плиткой. | H94: 25 кг | I94: 1,3-1,5 кг/м 2 | J94: 2-15 мм | K94: C0T, ГОСТ Р 56387-2018 | L94: — | N94: https://osnovit.ru/catalog/plitochnye-klei/bazpliks-as10-kley-standart-dlya-keramicheskoy-plitki-osnovit/ | O94: Есть таблица расхода по размеру плитки (до 10 см — 2,4 … до 25 см — 6,1 кг/м²). На странице названы «Сертификат» и «Техническая карта Базпликс AC10», но pdf во входе нет.
A95: Основит | B95: Плиточные клеи | C95: да | D95: Основит Белпликс AC141 W | E95: Клей плиточный белый Основит Белпликс AC141 W [С1T] | F95: 1 | G95: Белый плиточный клей Основит Белпликс AC141 W предназначен для облицовки стен и пола плитами из мрамора, цветной и прозрачной стеклянной плиткой, декоративной мозаикой, стекло-блоками, гранитом, натуральным и искусственным камнем. | H95: 5 кг, 25 кг | I95: 1,3-1,4 кг/м 2 | J95: 2-20 мм | K95: ГОСТ Р 56387-2018 | L95: — | M95: Супер белый цвет | N95: https://osnovit.ru/catalog/plitochnye-klei/belpliks-ac141-w-s1t-h-kley-plitochnyy-belyy-dlya-keramicheskoy-mozaiki-keramicheskoy-keramogranit/ | O95: В названии и классе стоит кириллическая «С» («С1T»). Фразы «для внутренних и наружных работ» нет, но рекомендован для балконов, террас, цоколей, фасадов и бассейнов (плитка до 30х30 см). W — белый цвет, входит в код модели. Тех. карта и сертификат названы, pdf во входе нет.
A96: Основит | B96: Плиточные клеи | C96: да | D96: Основит Гранипликс AC14 | E96: Клей плиточный зимний Основит Гранипликс AC14 F [C2T] 25 кг | F96: 2 | G96: Плиточный клей Основит Гранипликс AC14 F зимний предназначен для укладки керамической и клинкерной плитки, плит из керамогранита, натурального и искусственного камня (вес до 800 г / 100 см²) при температуре окружающей среды и основания от + 10°С до -10°С. | H96: 25 кг, 5 кг | I96: 1,3-1,5 кг/м 2 | J96: 2-15 мм | K96: C2TE, ГОСТ Р 56387-2018 | L96: есть | M96: серый | N96: https://osnovit.ru/catalog/plitochnye-klei/osnovit-granipliks-as14-f-zimniy-kley-granit-dlya-naturalnogo-kamnya-keramogranita-klinkernoy-i-kera/ | O96: Зимняя модификация AC14 (id osnovit__catalog__plitochnye-klei__granipliks-as14): класс C2T вместо C2TE, жизнеспособность 1 час вместо 4. На странице: «Возможна фасовка материала в мешок Гранипликс AC14 со стикером «зимний»». Таблица расхода по размеру плитки отличается от летней.
A97: Основит | B97: Плиточные клеи | C97: да | D97: Основит Гранипликс AC15 R | E97: Клей плиточный быстротвердеющий Основит Гранипликс AC15 R [C1TF] | F97: 1 | G97: Плиточный клей Основит Гранипликс AC15 R предназначен для выполнения ремонтных работ и ускоренной облицовки стен и пола искусственным и натуральным камнем, керамической плиткой и керамогранитом (вес до 800 г / 100 см²). | H97: 5 кг, 25 кг | J97: 1-10 мм | K97: C1TF, ГОСТ Р 56387-2018 | L97: — | N97: https://osnovit.ru/catalog/plitochnye-klei/skorpliks-t-15/ | O97: Быстротвердеющий (F): затирка и хождение через 3 часа. Расход только таблицей по размеру плитки (до 10 см — 2,1 … до 25 см — 5,2 кг/м²), consumption_quote пуст. Не путать с Максипликс AC15 [C2T] (другой продукт, тоже «AC15»). Адрес …/skorpliks-t-15/ (старое имя «Скорпликс»?). В характеристиках класс «С1TF» с кириллической «С». Тех. карта и сертификат названы, pdf во входе нет.
A98: Основит | B98: Плиточные клеи | C98: да | D98: Основит Максипликс AC15 | E98: Клей плиточный высокопрочный Основит Максипликс AC15 [C2T] 25 кг | F98: 1 | G98: Плиточный клей Основит Максипликс AC15 предназначен для облицовки стен и пола крупноформатными плитами из мрамора и гранита, натуральным и искусственным камнем(клинкерная плитка), керамогранитом и керамической плиткой. | H98: 25 кг | I98: 1,3-1,4 кг/м 2 | J98: 2-30 мм | K98: C2T , ГОСТ Р 56387-2018 | L98: — | N98: https://osnovit.ru/catalog/plitochnye-klei/maksipliks-ac151-s2t-kley-plitochnyy-oblitsovki-sten-pola-iskusstvennym-naturalnym-kamnem-keramogranitom/ | O98: Характеристики даны двумя столбцами — г. Коломна и г. Бердск; взяты значения первого (Коломна). Различие: «Хождение через» 24 часа (Коломна) и 12 часов (Бердск). Две тех. карты (вторая — «г. Бердск»), pdf во входе нет. Адрес …/maksipliks-ac151-s2t-…/. Возможно применение в системах скреплённой теплоизоляции.
A99: Основит | B99: Плиточные клеи | C99: да | D99: Основит Максипликс AC16 | E99: Клей плиточный профессиональный Основит Максипликс AC16 [C2TE] 25 кг | F99: 1 | G99: Плиточный клей Основит Максипликс AC16 беспылевой предназначен для облицовки стен и пола крупноформатными плитами из мрамора и гранита, натуральным и искусственным камнем(клинкерная плитка), керамогранитом и керамической плиткой. | H99: 25 кг | I99: 1,2-1,4 кг/м² | J99: 1-12 мм | K99: C2TE, ГОСТ Р 56387-2018 | L99: — | M99: серый | N99: https://osnovit.ru/catalog/plitochnye-klei/maksipliks-t-16/ | O99: Беспылевой; «Возможно применение в системах скрепленной теплоизоляции». Документ «Техническая карта Максипликс AC16» — без ссылки во входе.
A100: Основит | B100: Плиточные клеи | C100: да | D100: Основит Максипликс AC161 E | E100: Клей плиточный высокоэластичный Основит Максипликс AC161 Е 25 кг | F100: 1 | G100: высокоэластичный беспылевой предназначен для облицовки стен и пола керамической плиткой и керамогранитом, плитами из мрамора и гранита, натуральным и искусственным камнем(клинкерная плитка) | H100: 25 кг | I100: 1,2 кг/м² | J100: 1-12 мм | K100: C2TE S1, ГОСТ Р 56387-2018 | L100: — | N100: https://osnovit.ru/catalog/plitochnye-klei/maksipliks-as16-e/ | O100: В заголовке буква Е в коде модели кириллическая; product_code и series_key записаны латиницей. Беспылевой, класс C2TE S1 (в заголовке класса нет, в разделе — «МАКСИПЛИКС АС161 Е [C2TE S1]»). Основания включают дерево, фанеру, ДСП внутри помещений, молодой бетон. Адрес …/maksipliks-as16-e/. Тех. карта и сертификат названы, pdf во входе нет.
...

Sheet Карточки
A1: Производитель | B1: Тип страницы | C1: Название (h1) | D1: Товар | E1: Вариант | F1: Наш тип | G1: Сухая | H1: Назначение — дословно | I1: Фасовка — дословно | J1: Расход — дословно | K1: Метки | L1: Ссылка
A2: Dauer | B2: product | C2: Dauer BRICK.COLOR 250 цветная кладочная смесь армированная | D2: Dauer BRICK.COLOR 250 | F2: masonry_colored | G2: yes | H2: Для монтажа и одновременной отделки швов кладочных элементов с водопоглощением от 6 до 12% | I2: 3,5 – 4,5 литра воды на мешок 25 кг или 7 – 9 литров на мешок 50 кг | K2: Новинка | L2: https://dauer.ru/catalog/montazhnye-i-kladochnye/dauer-brick-color-250/
A3: Dauer | B3: product | C3: Dauer BRICK.COLOR 251 цветная кладочная смесь армированная | D3: Dauer BRICK.COLOR 251 | F3: masonry_colored | G3: yes | H3: Для монтажа и одновременной отделки швов кладочных элементов с водопоглощением от 5 до 18% (полнотелый и пустотелый облицовочный керамический кирпич, кирпич ручной формовки, рядовой керамический и плотный силикатный кирпич, кирпичи или блоки из бетона и натурального камня). | I3: 3,5 – 4,5 литра воды на мешок 25 кг или 7 – 9 литров на мешок 50 кг | K3: Новинка | L3: https://dauer.ru/catalog/montazhnye-i-kladochnye/dauer-brick-color-251/
A4: Dauer | B4: product | C4: Dauer BRICK.COLOR 252 цветная кладочная смесь армированная | D4: Dauer BRICK.COLOR 252 | F4: masonry_colored | G4: yes | H4: Для монтажа и одновременной отделки швов кладочных элементов с водопоглощением от 1 до 5% (полнотелый и пустотелый облицовочный клинкерный кирпич, блоки из бетона и натурального камня). | I4: Смесь поставляется в бумажных мешках. | K4: Новинка | L4: https://dauer.ru/catalog/montazhnye-i-kladochnye/dauer-brick-color-252/
A5: Dauer | B5: product | C5: Dauer BRICK.COLOR 253 кладочная смесь для рядового кирпича | D5: Dauer BRICK.COLOR 253 | F5: masonry_ordinary | G5: yes | H5: Предназначена для монтажа забутовочных кладочных элементов (полнотелый и пустотелый керамический кирпич, натуральный камень, рядовой керамический и плотный силикатный кирпич, кирпичи из бетона). | I5: 3,25 – 3,75 литра воды на мешок 25 кг или 6,5 – 7,5 литров на мешок 50 кг | K5: Новинка | L5: https://dauer.ru/catalog/montazhnye-i-kladochnye/dauer-brick-color-253/
A6: Dauer | B6: product | C6: Dauer CONECTOR® 02 Клей Оптимум C0 Т | D6: Dauer CONECTOR 02 | F6: tile_adhesive | G6: yes | H6: Для укладки на пол и стены керамической плитки по ГОСТ 13996 (со средним и высоким водопоглощением) и других облицовочных материалов с водопоглощением не менее 5%. Применяется внутри помещений с любым уровнем влажности. | I6: 25 кг. | J6: 1,3 – 1,4 кг/м² | L6: https://dauer.ru/catalog/plitochnye-klei/conector-02/
A7: Dauer | B7: product | C7: Dauer CONECTOR® 14 Клей Армированный С1 TЕ | D7: Dauer CONECTOR 14 | F7: tile_adhesive | G7: yes | H7: Для выполнения работ по облицовке фасадов выше цокольной части и помещений с любым уровнем влажности. Применяется для укладки керамической плитки, керамогранита и натурального камня весом до 150 кг/м2. | I7: 25 кг. | J7: 1,3 – 1,4 кг/м² | L7: https://dauer.ru/catalog/plitochnye-klei/conector-14/
A8: Dauer | B8: product | C8: Dauer CONECTOR® 22 Клей высокоэффективный С2 T | D8: Dauer CONECTOR 22 | F8: tile_adhesive | G8: yes | H8: Для наружных и внутренних облицовочных работ фасадов зданий и сооружений (включая цокольную часть) крупноформатными облицовочными материалами (керамическая и клинкерная плитка, натуральный камень и керамогранит). | I8: 25 кг. | J8: 1,3 – 1,4 кг/м² | L8: https://dauer.ru/catalog/plitochnye-klei/conector-force-22-kley-vysokoeffektivnyy-s2-t-gost-r-56387/
A9: Dauer | B9: product | C9: Dauer CONECTOR® 22 Макс Клей Армированный С2 TЕ | D9: Dauer CONECTOR 22 Макс | F9: tile_adhesive | G9: yes | H9: Для наружных и внутренних облицовочных работ фасадов зданий и сооружений (включая цокольную часть) крупноформатными облицовочными материалами (керамическая и клинкерная плитка, натуральный камень и керамогранит). | I9: 25 кг. | J9: 1,3 – 1,4 кг/м² | L9: https://dauer.ru/catalog/plitochnye-klei/conector-22-max/
A10: Dauer | B10: product | C10: Dauer CONECTOR® Плюс Клей Универсальный C1 T | D10: Dauer CONECTOR Плюс | F10: tile_adhesive | G10: yes | H10: Для укладки на пол и стены керамической и клинкерной плитки, керамогранита и натурального камня (кроме мрамора, базальта, габбро) весом до 80 кг/м². | I10: 25/40 кг. | J10: 1,3 – 1,4 кг/м² | K10: Хит | L10: https://dauer.ru/catalog/plitochnye-klei/conector-home-plus-kley-universalnyy-c1-gost-r-56387-2018/
A11: Dauer | B11: product | C11: Dauer FINNER® 40W Шпатлевка цементная армированная базовая белая | D11: Dauer FINNER 40 | E11: белая (W) | F11: putty_cement | G11: yes | H11: Для толстослойного и финишного выравнивания (слой от 1 до 15 мм) поверхности фасадов, стен и потолков внутри всех видов жилых и нежилых помещений, в т.ч. влажных и неотапливаемых: подвалы, балконы и лоджии, паркинги, лестничные пролеты, марши, склады, душевые и ванные комнаты. | I11: 25 кг. | J11: 0,9 кг/м2 | L11: https://dauer.ru/catalog/shpatlevki/finner-exter-40w-shpatlevka-tsementnaya-armirovannaya-bazovaya-belaya/
A12: Dauer | B12: product | C12: Dauer FINNER® 40G Шпатлевка цементная армированная базовая серая | D12: Dauer FINNER 40 | E12: серая (G) | F12: putty_cement | G12: yes | H12: Для толстослойного и финишного выравнивания (слой от 1 до 15 мм) поверхности фасадов, стен и потолков внутри всех видов помещений, в т.ч. влажных и неотапливаемых. | I12: 25 кг. | J12: 0,9 кг/м2 | L12: https://dauer.ru/catalog/shpatlevki/finner-40g/
A13: Dauer | B13: product | C13: Dauer FINNER® 41W Шпатлевка цементная финишная белая 180/6,5/F50 ГОСТ 33699 | D13: Dauer FINNER 41 | E13: белая (W) | F13: putty_cement | G13: yes | H13: Для финишного выравнивания (слой от 0,2 до 5 мм) поверхности фасадов, стен и потолков, внутри всех видов помещений, в т.ч. влажных и неотапливаемых: подвалы, лоджии, балконы, паркинги, лестничные пролеты, марши, склады, душевые и ванные комнаты. | I13: 20 кг. | J13: 1 кг/м2 | L13: https://dauer.ru/catalog/shpatlevki/finner-exter-41w-shpatlevka-tsementnaya-finishnaya-belaya/
A14: Dauer | B14: product | C14: Dauer FINNER® 41G Шпатлевка цементная финишная серая | D14: Dauer FINNER 41 | E14: серая (G) | F14: putty_cement | G14: yes | H14: Для финишного выравнивания (слой от 0,2 до 5 мм) поверхности фасадов, стен и потолков, внутри всех видов помещений, в т.ч. влажных и неотапливаемых: подвалы, лоджии, балконы, паркинги, лестничные пролеты, марши, склады, душевые и ванные комнаты. Используется для выравнивания поверхности под нанесение финишных декоративных покрытий и многослойное окрашивание ЛКМ. | I14: 20 кг. | J14: 0,9 кг/м2 | L14: https://dauer.ru/catalog/shpatlevki/finner-exter-41g-shpatlevka-tsementnaya-finishnaya-seraya/
A15: Dauer | B15: product | C15: Dauer FINNER® 43W Шпатлевка гипсовая универсальная белая | D15: Dauer FINNER 43 | E15: белая (W) | F15: putty_gypsum | G15: yes | H15: Внутри сухих отапливаемых помещений для толстослойного и финишного выравнивания (слой от 1 до 20 мм) поверхности стен и потолков под дальнейшую отделку обоями и нанесения финишных декоративных покрытий; для заделки трещин, выбоин, раковин слоем до 20 мм, для заполнения швов ГВЛ, ГКЛ с обязательным применением армирующей ленты. | I15: 20 кг. | J15: 0,9 кг/м² | L15: https://dauer.ru/catalog/shpatlevki/finner-43/
A16: Dauer | B16: product | C16: Dauer IMMER® 60 Грунт глубокого проникновения | D16: Dauer IMMER 60 | F16: primer | G16: no | H16: Для обработки и обеспыливания минеральных оснований, под последующее нанесение отделочных материалов: цементных и гипсовых штукатурок, цементных, гипсовых и полимерных шпаклёвок, плиточных и монтажных клеёв, лакокрасочных материалов, обоев и других финишных декоративных покрытий. | I16: e 10 л / НЕТТО 10 кг | J16: 100-120 мл/м² | K16: Новинка, Новая, улучшенная рецептура | L16: https://dauer.ru/catalog/grunty/immer-made-60-grunt-bazovyy-ukreplyayushchiy-na-akrilovoy-osnove/
A17: Dauer | B17: product | C17: Dauer IMMER® 65 Про Грунт глубокого проникновения | D17: Dauer IMMER 65 | F17: primer | G17: no | H17: Для предварительной обработки и обеспыливания минеральных оснований. Рекомендуется для упрочнения старых, рыхлых, непрочных и сильновпитывающих оснований. | I17: 5 л./10 л. | J17: 100-120 мл/м² | K17: Новинка, Новая, улучшенная рецептура | L17: https://dauer.ru/catalog/grunty/immer-made-65-grunt-glubokogo-proniknoveniya/
A18: Dauer | B18: product | C18: Dauer PLATTER® 50 Стяжка высокопрочная армированная | D18: Dauer PLATTER 50 | F18: floor_screed | G18: yes | H18: Применяется для базового толстослойного выравнивания полов, для устройства контактных стяжек и стяжек на разделительном слое, в том числе "плавающих". | I18: 25 кг. | J18: 18 кг/м² | K18: Новинка | L18: https://dauer.ru/catalog/materialy-dlya-ustroystva-polov/dauer-platter-50/
A19: Dauer | B19: product | C19: Dauer PLATTER® 55 Наливной пол универсальный быстротвердеющий | D19: Dauer PLATTER 55 | F19: floor_self_leveling | G19: yes | H19: Для ручного и механизированного выравнивания оснований (от 2 до 100 мм) под последующую укладку напольных покрытий: ламинат, линолеум и ковролин, керамическая и керамогранитная плитка, другие выстилающие покрытия. | I19: 20 кг. | J19: 1,4-1,6 кг/м² | L19: https://dauer.ru/catalog/materialy-dlya-ustroystva-polov/platter-self-55-eco-nalivnoy-pol-universalnyy-bystrotverdeyushchiy-rk5-vtb4-v12-5-gost-31358-2019/
A20: Dauer | B20: product | C20: Dauer PLATTER® 57 Наливной пол армированный быстротвердеющий | D20: Dauer PLATTER 57 | F20: floor_self_leveling | G20: yes | H20: Для ручного и механизированного выравнивания оснований (от 1 до 15 мм) под последующую укладку напольных покрытий. | I20: 20 кг. | J20: 1,5-1,6 кг/м² | L20: https://dauer.ru/catalog/materialy-dlya-ustroystva-polov/platter-self-57-nalivnoy-pol-tonkosloynyy-bystrotverdeyushchiy-klass-v15-gost-31358/
A21: Dauer | B21: product | C21: Dauer PLATTER® 59 Наливной пол армированный высокопрочный | D21: Dauer PLATTER 59 | F21: floor_self_leveling | G21: yes | H21: Для ручного и механизированного выравнивания оснований от 2 до 30 мм, с возможностью локального выравнивания до 50 мм, эксплуатируемых в жилых, офисных, торговых или иных общественных помещениях с умеренной и повышенной влажностью, в условиях умеренных и значительных нагрузок, под последующую укладку напольных покрытий, а также под проведение облицовочных работ плитами из керамогранита или натурального камня. | I21: 25 кг. | J21: 1,7 кг/м2 | L21: https://dauer.ru/catalog/materialy-dlya-ustroystva-polov/platter-self-59-nalivnoy-pol-vysokoprochnyy-rk6-vtb4-v20-f50-gost-31358/
A22: Dauer | B22: product | C22: Dauer QUADER D600 клей для блоков усиленный | D22: Dauer QUADER D600 | F22: block_adhesive | G22: yes | H22: Для возведения стен и перегородок из блоков на основе газо- и пенобетона, силикатного пенобетона, полистиролбетона и других ячеистых блоков. | I22: 25 кг, 40 кг | J22: Расход раствора при слое шва 2 мм | K22: Хит | L22: https://dauer.ru/catalog/montazhnye-i-kladochnye/block-d600-kley-montazhnyy/
A23: Dauer | B23: product | C23: Dauer SAVER 707 Гидроизоляция готовая полимерная | D23: Dauer SAVER 707 | F23: waterproofing_liquid | G23: no | H23: Гидроизоляция готовая на полимерной основе, предназначена для создания эластичного гидроизоляционного покрытия на горизонтальных и вертикальных поверхностях в помещениях под последующую укладку керамической и клинкерной плитки, керамогранита, натурального и искусственного камня, подверженных периодическому увлажнению (ванных, душевых, туалетах, кухнях и т.д.). | I23: 14 кг. | J23: 1,4 кг/м2 | L23: https://dauer.ru/catalog/gidroizolyatsiya/dauer-saver-707/
A24: Dauer | B24: product | C24: Dauer SLIDER® 301 Штукатурка цементно-известковая выравнивающая облегченная | D24: Dauer SLIDER 301 | F24: plaster_cement | G24: yes | H24: Штукатурка цементно-известковая выравнивающая облегченная SLIDER® 301 предназначена для ручного и механизированного высококачественного выравнивания (слой 5 – 40 мм) поверхности фасадов зданий и сооружений, стен внутри всех видов помещений в т.ч. влажных и неотапливаемых: подвалы, балконы и лоджии, паркинги, лестничные пролеты, марши, склады, другие помещения с переменной влажностью. | I24: 40 кг. | J24: 12,5 кг/м2 | K24: Новинка | L24: https://dauer.ru/catalog/shtukaturki/slider-fasad-301/
A25: Dauer | B25: product | C25: Dauer SLIDER® 302 Штукатурка цементно-известковая гладкая | D25: Dauer SLIDER 302 | F25: plaster_cement | G25: yes | H25: Штукатурка цементно-известковая гладкая Dauer SLIDER® 302 предназначена для ручного и механизированного высококачественного выравнивания (слой 5 – 40 мм) поверхности фасадов зданий и сооружений, стен внутри всех видов помещений в т.ч. влажных и неотапливаемых: подвалы, балконы и лоджии, паркинги, лестничные пролеты, марши, склады, другие помещения с переменной влажностью. | I25: 25 кг. | J25: 12,5 кг/м2 | K25: Новинка | L25: https://dauer.ru/catalog/shtukaturki/slider-fasad-302/
A26: Dauer | B26: product | C26: Dauer SLIDER® 31 Штукатурка цементная мелкофракционная гладкая | D26: Dauer SLIDER 31 Slim | F26: plaster_cement | G26: yes | H26: Для ручного и механизированного выравнивания слоем от 3 мм. (локально) до 30 мм. поверхности фасадов, стен внутри всех видов помещений, в т.ч. влажных и неотапливаемых: подвалы, лоджии, паркинги, лестничные пролеты, марши, склады, душевые и ванные комнаты. | I26: 25 кг, 40 кг | J26: 12 - 13 кг/м² | K26: Хит | L26: https://dauer.ru/catalog/shtukaturki/slider-fasad-31-slim-shtukaturka-tsementnaya-melkofraktsionnaya-gladkaya-kp-iii-gost-33083-2014/
A27: Dauer | B27: product | C27: Dauer SLIDER® 31 Фибра Штукатурка цементная выравнивающая армированная | D27: Dauer SLIDER 31 Фибра | F27: plaster_cement | G27: yes | H27: Для ручного и механизированного выравнивания (слоем 5 - 40 мм) поверхности фасадов, стен внутри всех видов помещений, в т.ч. влажных и неотапливаемых: подвалы, балконы и лоджии, паркинги, лестничные пролеты, марши, склады, душевые и ванные комнаты. Для ремонта сколов, выбоин, раковин, трещин глубиной до 50 мм. | I27: 25 кг, 40 кг | J27: 14 - 15 кг/м² | K27: Хит | L27: https://dauer.ru/catalog/shtukaturki/slider-fasad-31-fibro-shtukaturka-tsementnaya-vyravnivayushchaya-armirovannaya-kp-iii-gost-33083-201/
A28: Dauer | B28: product | C28: Dauer SLIDER® 312 Штукатурка цементная гладкая с перлитом | D28: Dauer SLIDER 312 | F28: plaster_cement | G28: yes | H28: Для высококачественного выравнивания (слой 3 – 40 мм) поверхности фасадов зданий и сооружений, стен внутри всех видов помещений в т.ч. влажных и неотапливаемых: подвалы, балконы и лоджии, паркинги, лестничные пролеты, марши, склады, душевые и ванные комнаты. | I28: 30 кг. | J28: 12 кг/м2 | L28: https://dauer.ru/catalog/shtukaturki/slider-312/
A29: Dauer | B29: product | C29: Dauer SLIDER® 321 штукатурка цементная высокопрочная фасадная | D29: Dauer SLIDER 321 | F29: plaster_cement | G29: yes | H29: Штукатурка цементная высокопрочная фасадная SLIDER® 321 предназначена для ручного и механизированного высококачественного выравнивания (слой 10 – 40 мм, локально от 5 мм.) поверхности фасадов и цоколей зданий и сооружений, стен снаружи и внутри всех видов помещений в т.ч. влажных и неотапливаемых: подвалы, балконы и лоджии, паркинги, лестничные пролеты, марши, склады, другие помещения с переменной влажностью. | I29: 40 кг. | J29: 16 кг/м2 | K29: Новинка | L29: https://dauer.ru/catalog/shtukaturki/dauer-slider-321/
A30: Dauer | B30: product | C30: Dauer SLIDER® 36W Штукатурка гипсовая универсальная белая | D30: Dauer SLIDER 36 | E30: белая (W) | F30: plaster_gypsum | G30: yes | H30: Для машинного и ручного выравнивания стен: сплошного (от 5 до 50 мм) и частичного при локальном выравнивании (до 60 мм), выравнивания потолков (до 10 мм) – внутри помещений с умеренной влажностью под последующую отделку (оклейку обоями, многослойное окрашивание, шпатлевание). | I30: 30 кг. | J30: 0,9 – 1,0 кг/м² | K30: Хит | L30: https://dauer.ru/catalog/shtukaturki/slider-interier-36w-shtukaturka-gipsovaya-universalnaya-belaya-90-2-0-gost-r-58279-2018/
A31: Dauer | B31: product | C31: Dauer SLIDER® 36 Штукатурка гипсовая универсальная серая | D31: Dauer SLIDER 36 | E31: серая | F31: plaster_gypsum | G31: yes | H31: Для машинного и ручного выравнивания стен: сплошного (от 5 до 50 мм) и частичного при локальном выравнивании (до 60 мм), выравнивания потолков (до 10 мм) – внутри помещений с умеренной влажностью под последующую отделку (финишное тонкослойное шпатлевание, оклейку обоями, многослойное окрашивание). | I31: 30 кг. | J31: 9 – 10 кг/м² | L31: https://dauer.ru/catalog/shtukaturki/slider-36/
A32: Dauer | B32: product | C32: Dauer SLIDER® 37W Штукатурка гипсовая тёплая армированная белая | D32: Dauer SLIDER 37 | E32: белая (W) | F32: plaster_gypsum | G32: yes | H32: Для машинного и ручного выравнивания стен: сплошного (от 3 до 50 мм) и частичного, при локальном выравнивании (до 80 мм), для выравнивания потолков (до 30 мм), внутри помещений с умеренной влажностью под последующую отделку (финишное тонкослойное шпатлевание, оклейку обоями, многослойное окрашивание). | I32: 30 кг. | J32: 0,8 кг/м² | L32: https://dauer.ru/catalog/shtukaturki/slider-37w/
A33: Dauer | B33: product | C33: Dauer SLIDER® 37 Штукатурка гипсовая теплая армированная | D33: Dauer SLIDER 37 | E33: серая | F33: plaster_gypsum | G33: yes | H33: Для машинного и ручного выравнивания стен: сплошного (от 3 до 50 мм) и частичного, при локальном выравнивании (до 80 мм), для выравнивания потолков (до 30 мм), внутри помещений с умеренной влажностью под последующую отделку (финишное тонкослойное шпатлевание, оклейку обоями, многослойное окрашивание). | I33: 30 кг. | J33: 0,8 кг/м² | L33: https://dauer.ru/catalog/shtukaturki/slider-37/
A34: Dauer | B34: product | C34: Dauer SLIDER® 38W Штукатурка гипсовая легкая с перлитом белая | D34: Dauer SLIDER 38 | E34: белая (W) | F34: plaster_gypsum | G34: yes | H34: Для машинного и ручного выравнивания стен: сплошного (от 3 до 50 мм) и частичного, при локальном выравнивании (до 80 мм), для выравнивания потолков (до 30 мм), внутри помещений с умеренной влажностью под последующую отделку (шпатлевание, оклейку обоями, многослойное окрашивание). | I34: 30 кг. | J34: 9 кг/м² | K34: Хит | L34: https://dauer.ru/catalog/shtukaturki/slider-38w/
A35: Dauer | B35: product | C35: Dauer SLIDER® 38 Штукатурка гипсовая легкая с перлитом | D35: Dauer SLIDER 38 | E35: серая | F35: plaster_gypsum | G35: yes | H35: Для машинного и ручного выравнивания стен: сплошного (от 3 до 50 мм) и частичного, при локальном выравнивании (до 80 мм), для выравнивания потолков (до 30 мм), внутри помещений с умеренной влажностью под последующую отделку (шпатлевание, оклейку обоями, многослойное окрашивание). | I35: 30 кг. | J35: 0,8 кг/м² | K35: Хит | L35: https://dauer.ru/catalog/shtukaturki/slider-38/
A36: Dauer | B36: product | C36: Dauer SLIDER® 39 Штукатурка гипсовая универсальная влагостойкая | D36: Dauer SLIDER 39 | F36: plaster_gypsum | G36: yes | H36: Для машинного и ручного выравнивания стен: сплошного (от 5 до 50 мм) и частичного при локальном выравнивании (до 80 мм), для выравнивания потолков (до 20 мм), внутри помещений с нормальной и повышенной влажностью под последующую отделку: финишное тонкослойное шпатлевание, оклейку обоями, многослойное окрашивание, облицовку керамической плиткой малого формата (размер грани не более 30 см) с тщательной затиркой межплиточных швов. | I36: 30 кг. | J36: 10 – 11 кг/м² | L36: https://dauer.ru/catalog/shtukaturki/slider-39/
A37: Dauer | B37: product | C37: Dauer SLIDER® Адгезив высокопрочный обрызг | D37: Dauer SLIDER Адгезив | F37: plaster_facade_base | G37: yes | H37: Штукатурный цементный обрызг высокопрочный SLIDER® Адгезив используется для создания шероховатого, структурного, слоя на гладких слабовпитывающих поверхностях и основаниях, для укрепления и выравнивания впитывающей способности комбинированных оснований. | I37: 25 кг. | J37: 1,6 кг/м2 | K37: Новинка | L37: https://dauer.ru/catalog/shtukaturki/slider-fasad-adhesive/
A38: Dauer | B38: product | C38: Dauer SLIDER® Легкая Штукатурка цементно-известковая легкая | D38: Dauer SLIDER Легкая | F38: plaster_cement | G38: yes | H38: Легкая штукатурка для ручного и механизированного высококачественного выравнивания (слой 5 – 50 мм, локально до 80 мм) поверхности фасадов зданий и сооружений, стен внутри всех видов помещений в т.ч. влажных и неотапливаемых: подвалы, балконы и лоджии, паркинги, лестничные пролеты, марши, склады, другие помещения с переменной влажностью, а также для предварительного выравнивания потолков. | I38: 30 кг. | J38: 9 - 10 кг/м2 | K38: Новинка | L38: https://dauer.ru/catalog/shtukaturki/slider-light/
A39: Dauer | B39: product | C39: Dauer TEFIX LM Кладочный раствор для теплой керамики | D39: Dauer TEFIX LM | F39: masonry_thermal | G39: yes | H39: Предназначен для возведения несущих и ограждающих конструкций из «теплой» керамики, газобетона и легкого пустотелого кирпича, а также блоков из бетона на пористых заполнителях (керамзитобетон). | I39: 20 кг. | J39: Расход раствора при слое шва 12 мм | K39: Хит | L39: https://dauer.ru/catalog/montazhnye-i-kladochnye/tefix-lm-kladochnyy-rastvor/
A40: Dauer | B40: product | C40: Dauer TEFIX SM Кладочный раствор теплоизоляционный | D40: Dauer TEFIX SM | F40: masonry_thermal | G40: yes | H40: Предназначен для возведения несущих и ограждающих стен из поризованных керамических блоков, легких блоков из ячеистого бетона (в т.ч. пено- и газобетон), а также блоков из бетона на пористых заполнителях (керамзитобетон). | I40: 25 кг. | J40: РАСХОД РАСТВОРА ПРИ СЛОЕ ШВА 12 мм | L40: https://dauer.ru/catalog/montazhnye-i-kladochnye/quader-tefix-sm/
A41: Dauer | B41: product | C41: Dauer TEFIX SW Кладочный раствор для теплой керамики | D41: Dauer TEFIX SW | F41: masonry_thermal | G41: yes | H41: Предназначен для возведения несущих и ограждающих конструкций из «теплой» керамики, газобетона и легкого пустотелого кирпича, а также блоков из бетона на пористых заполнителях (керамзитобетон). | I41: 17,5 кг. | K41: Новинка | L41: https://dauer.ru/catalog/montazhnye-i-kladochnye/tefix-sw/
A42: Dauer | B42: product | C42: Dauer® Сухая смесь М-150 Универсальная | D42: Dauer М-150 Универсальная | F42: masonry_universal_cps | G42: yes | H42: Сухая смесь универсальная предназначена для возведения стен и перегородок из кирпича и мелкоштучных элементов, для работ по заделке полостей, выбоин и трещин, производства различных монтажных и штукатурных работ, а также для укладки тротуарной плитки. | I42: 30 кг, 40 кг, 50 кг | J42: 19 кг/м² | L42: https://dauer.ru/catalog/tsementno-peschanye-smesi/sukhaya_smes_m_150_universalnaya/
A43: Dauer | B43: product | C43: Dauer® Сухая смесь М-150 Штукатурная | D43: Dauer М-150 Штукатурная | F43: masonry_universal_cps | G43: yes | H43: Сухая смесь штукатурная предназначена для оштукатуривания стен из бетона, кирпича, камня. | I43: на 1 мешок 50 кг | J43: 19 кг/м² | L43: https://dauer.ru/catalog/tsementno-peschanye-smesi/sukhaya_smes_m_150_shtukaturnaya/
A44: Dauer | B44: product | C44: Dauer® Сухая смесь М-200 Монтажно-кладочная | D44: Dauer М-200 Монтажно-кладочная | F44: masonry_universal_cps | G44: yes | H44: Сухая смесь монтажно-кладочная предназначена для выполнения общестроительных работ: устройство "мокрых" стяжек; заделка швов, трещин, выбоин, углублений; возведение стен и конструкций из полнотелого рядового кирпича, полнотелых бетонных блоков и природного камня. | I44: на 1 мешок 50 кг | J44: 20 кг/м² | L44: https://dauer.ru/catalog/tsementno-peschanye-smesi/sukhaya_smes_m_200_montazhno_kladochnaya/
A45: Dauer | B45: product | C45: Dauer® Сухая смесь М-300 Пескобетон | D45: Dauer М-300 Пескобетон | F45: masonry_universal_cps | G45: yes | H45: Сухая смесь пескобетон предназначена для выполнения общестроительных работ: устройство высокопрочных стяжек ("мокрого" типа); заделка швов, трещин, выбоин, углублений; крепление металлических элементов и монтаж железобетонных конструкций; возведение стен и конструкций из полнотелого рядового кирпича, полнотелых бетонных блоков и природного камня. | I45: 30 кг, 40 кг, 50 кг | J45: 20 кг/м² | L45: https://dauer.ru/catalog/tsementno-peschanye-smesi/sukhaya_smes_m_300_peskobeton/
A46: Dauer | B46: product | C46: Dauer® Сухая смесь М-400 Пескобетон высокопрочный | D46: Dauer М-400 Пескобетон высокопрочный | F46: masonry_universal_cps | G46: yes | H46: Сухая смесь пескобетон предназначена для выполнения общестроительных работ: устройство высокопрочных стяжек ("мокрого" типа); заделка швов, трещин, выбоин, углублений; крепление металлических элементов и монтаж железобетонных конструкций; возведение стен и конструкций из полнотелого рядового кирпича, полнотелых бетонных блоков и природного камня. | I46: 40 кг | J46: 20 кг/м² | K46: Новинка | L46: https://dauer.ru/catalog/tsementno-peschanye-smesi/sukhaya-smes-m-400-peskobeton-vysokoprochnyy/
A47: Основит | B47: product_group_landing | C47: Гидроизоляция Основит | F47: other | G47: unclear | L47: https://osnovit.ru/catalog/gidroizolyatsiya/
A48: Основит | B48: product_group_landing | C48: Смеси для пола Основит | F48: floor_self_leveling | G48: yes | H48: В ассортименте представлены все необходимые материалы для подготовки основания: от черновых стяжек до финишных наливных покрытий. | L48: https://osnovit.ru/catalog/smesi-dlya-ustroystva-pola/
A49: Основит | B49: product_group_landing | C49: Стяжки для пола Основит | F49: floor_screed | G49: yes | H49: Смеси Основит Стартолайн предназначены для предварительного выравнивания бетонных и цементно-песчаных оснований, устройства стяжек всех типов, включая «плавающие», и укрытия трубопроводов. | L49: https://osnovit.ru/catalog/styazhki/
A50: Основит | B50: product_group_landing | C50: Теплоизоляционные кладочные растворы Основит | F50: masonry_thermal | G50: unclear | H50: Теплоизоляционные кладочные смеси Основит Путформ решают эту задачу: они обладают пониженной теплопроводностью, высокой пластичностью и обеспечивают однородную кладку без теплопотерь через швы. | K50: Зима | L50: https://osnovit.ru/catalog/teploizolyatsionnye-kladochnye-rastvory/
A51: Основит | B51: product_group_landing | C51: Цветные кладочные растворы Основит | F51: masonry_colored | G51: unclear | H51: Облицовочный кладочный раствор Основит для кирпича с высоким водопоглощением | K51: Колеровка, Зима, Новинка | L51: https://osnovit.ru/catalog/tsvetnye-kladochnye-rastvory/
A52: Основит | B52: product_group_landing | C52: Шпаклевка Основит | F52: other | G52: unclear | H52: Шпаклевка — материал для финишного выравнивания поверхностей перед нанесением декоративных покрытий. | L52: https://osnovit.ru/catalog/shpaklevki/
A53: Основит | B53: product_group_landing | C53: Штукатурка Основит | F53: other | G53: unclear | H53: Штукатурка — это базовый материал для чернового выравнивания стен и потолков перед финишной отделкой. | L53: https://osnovit.ru/catalog/shtukaturki/
A54: Основит | B54: product_group_landing | C54: Ремонтный состав Основит | F54: concrete_repair | G54: unclear | H54: Для оперативного восстановления целостности оснований и надежной фиксации элементов разработаны ремонтные составы Основит Хардскрин. | L54: https://osnovit.ru/catalog/remont-i-zashchita-betona/
A55: Основит | B55: other | C55: РЕШЕНИЕ с газобетонным блоком, утеплителем и клинкерной плиткой | F55: other | G55: no | H55: Данное решение содержит все необходимые материалы для монтажа фасадной системы. | K55: Новинка | L55: https://osnovit.ru/catalog/resheniya-osnovit/reshenie-s-gazobetonnym-blokom-uteplitelem-i-klinkernoy-plitkoy/
A56: Основит | B56: other | C56: Решение с минеральной ватой | F56: other | G56: no | H56: Данное решение содержит все необходимые материалы для монтажа фасадной системы. | K56: Новинка | L56: https://osnovit.ru/catalog/resheniya-osnovit/sftk-s-mineralnoy-vatoy/
A57: Основит | B57: product | C57: Клей для блоков Основит PRO | D57: Основит PRO Клей для блоков | F57: block_adhesive | G57: yes | H57: Клей для блоков ОСНОВИТ PRO используется в тонкослойной кладке стен и перегородок. Предназначен для пазовых и беспазовых блоков и плит на основе ячеистого бетона (пено- и газобетон), газосиликата и силиката. | I57: 20 кг | J57: 1,3 кг/м² | L57: https://osnovit.ru/catalog/osnovit-pro/kley-dlya-blokov-osnovit-pro/
A58: Основит | B58: product | C58: Наливной пол быстротвердеющий Основит PRO | D58: Основит PRO Наливной пол быстротвердеющий | F58: floor_self_leveling | G58: yes | H58: Наливной пол быстротвердеющий ОСНОВИТ PRO предназначен для финишного выравнивания оснований слоем от 3 до 80 мм в жилых и офисных помещениях. | I58: 20 кг | J58: 14-15 кг/м² | L58: https://osnovit.ru/catalog/osnovit-pro/pol-nalivnoy-bystro-pro/
A59: Основит | B59: product | C59: Плиточный клей стандарт Основит PRO | D59: Основит PRO Плиточный клей стандарт | F59: tile_adhesive | G59: yes | H59: Плиточный клей стандарт ОСНОВИТ PRO предназначен для облицовки стен и пола керамической плиткой, а также укладки напольных плит из керамогранита. | I59: 25 кг | L59: https://osnovit.ru/catalog/osnovit-pro/plitochnyy-kley-standart-pro/
A60: Основит | B60: product | C60: Стяжка армированная Основит PRO | D60: Основит PRO Стяжка армированная | F60: floor_screed | G60: yes | H60: Стяжка ОСНОВИТ PRO предназначена для предварительного выравнивания оснований и устройства прочного пола в жилых, офисных, торговых и общественных помещениях. | I60: 25 кг | J60: 20 кг/м² | L60: https://osnovit.ru/catalog/osnovit-pro/styazhka-armirovannaya-osnovit-pro/
A61: Основит | B61: product | C61: Штукатурка гипсовая универсальная белая Основит PRO 30 кг | D61: Основит PRO Штукатурка гипсовая универсальная | E61: белая, 30 кг | F61: plaster_gypsum | G61: yes | H61: Гипсовая штукатурка ОСНОВИТ PRO предназначена для выравнивания стен и потолков в помещениях с нормальной влажностью. | I61: 30 кг | J61: 9-10 кг/м² | L61: https://osnovit.ru/catalog/osnovit-pro/shtukaturka-gipsovaya-uni-pro/
A62: Основит | B62: product | C62: Штукатурка цементная Основит PRO | D62: Основит PRO Штукатурка цементная | F62: plaster_cement | G62: yes | H62: Штукатурка Фасадная ОСНОВИТ PRO предназначена для выравнивания стен из кирпича, бетона и ячеистого бетона. | I62: 25 кг | J62: 16-17 кг/м² | L62: https://osnovit.ru/catalog/osnovit-pro/shtukaturka-fasadnaya-pro/
A63: Основит | B63: product | C63: Затирка эпоксидная Основит PRO 1 кг | D63: Основит PRO затирка эпоксидная | E63: 1 кг | F63: tile_grout_epoxy | G63: no | H63: Эпоксидная затирка ОСНОВИТ PRO предназначена для заполнения и защиты межплиточных швов шириной до 15 мм на полах и стенах в жилых, общественных и производственных помещениях, медицинских учреждениях и помещениях с высокой проходимостью. | I63: 1 кг | L63: https://osnovit.ru/catalog/epoksidnye-zatirki-i-materialy-dlya-ochistki-/epoksidnaya-zatirka-osnovit-pro/
A64: Основит | B64: product | C64: Клей гипсовый монтажный Основит PRO 20 кг | D64: Основит PRO клей гипсовый монтажный | F64: gypsum_mounting_adhesive | G64: yes | H64: Клей монтажный гипсовый ОСНОВИТ PRO Предназначен для монтажа перегородок из пазогребневых плит, ремонта пазогребневых плит, крепления гипсовых элементов декора и отделки, для бескаркасного монтажа гипсокартонных и гипсоволокнистых листов (ГКЛ и ГВЛ), приклеивания теплоизоляционных материалов. | I64: Вес упаковки 20 кг | J64: Расход сухой смеси при монтаже ПГП на 1 м2 1,5-2 кг | L64: https://osnovit.ru/catalog/osnovit-pro/kley-montazhnyy-gipsovyy-osnovit-pro/
A65: Основит | B65: product | C65: Плиточный клей усиленный Основит PRO | D65: Основит PRO плиточный клей усиленный | F65: tile_adhesive | G65: yes | H65: Плиточный клей усиленный ОСНОВИТ PRO предназначен для облицовки стен и полов керамической плиткой, керамогранитом, натуральным и искусственным камнем (вес до 600 г/100 см²). | I65: 25 кг | J65: 1,3-1,5 кг/м² | L65: https://osnovit.ru/catalog/plitochnye-klei/plitochnyy-kley-usilennyy-pro/
A66: Основит | B66: product | C66: Эмаль по дереву Univita Studio Аlbero EAс811 СМ3 | D66: Основит Univita Studio Albero EAс811 | E66: база А / база С; 0,9 л / 2,7 л | F66: paint | G66: no | H66: Рекомендуется для нанесения по деревянным основаниям, деревосодержащим основаниям, древесностружечным и древесноволокнистым плитам, а также по бетонным, кирпичным, оштукатуренным, зашпатлеванным поверхностям, гипсокартону, обоям и поверхностям, ранее окрашенным водно-дисперсионными красками и алкидными эмалями | I66: 0,9 л/2,7 л | J66: 10–14 м 2 /1 л | K66: Новинка | L66: https://osnovit.ru/catalog/emali/emal-po-derevu-univita-studio-albero-eas811-sm3/
A67: Основит | B67: product | C67: Краска интерьерная матовая Основит Univita Studio Lusso I | D67: Основит Univita Studio Lusso I | F67: paint | G67: no | H67: Предназначена для окрашивания стен и потолков в помещениях с нормальной и повышенной влажностью. | I67: 0,9 л/2,7 л/9 л | J67: 10–14 м 2 /1 л | K67: Колеровка | L67: https://osnovit.ru/catalog/kraski/interernaya-kraska-matovaya-moyushchayasya-ekstraprochnaya-dlya-sten-i-potolkov-osnovit-univita-stud/
A68: Основит | B68: product | C68: Краска интерьерная глубокоматовая Основит Univita Studio Lusso II | D68: Основит Univita Studio Lusso II | F68: paint | G68: no | H68: Предназначена для окрашивания стен и потолков в помещениях с нормальной и повышенной влажностью. | I68: 0,9 л/2,7 л/9 л | J68: 9–12 м 2 /1 л | K68: Колеровка | L68: https://osnovit.ru/catalog/kraski/interernaya-kraska-glubokomatovaya-moyushchayasya-dlya-sten-i-potolkov-osnovit-univita-studio-lusso-/
A69: Основит | B69: product | C69: Краска интерьерная глубокоматовая Основит Univita Studio Lusso III | D69: Основит Univita Studio Lusso III | F69: paint | G69: no | H69: Предназначена для окрашивания стен и потолков в помещениях с нормальной и повышенной влажностью. | I69: 0,9 л/2,7 л/9 л | J69: 8–11 м 2 /1 л | K69: Колеровка | L69: https://osnovit.ru/catalog/kraski/osnovit-univita-studio-lusso-iii-sas993-cm2/
A70: Основит | B70: product | C70: Эмаль по металлу Univita Studio Metallo EAс821 ПМ20 | D70: Основит Univita Studio Metallo EAс821 | E70: база А / база С; 0,9 л / 2,7 л | F70: paint | G70: no | H70: Эмаль ПО МЕТАЛЛУ: ОСНОВИТ UNIVITA Studio Metallo EAс821 ПМ20 акриловая полуматовая предназначена для создания гладкого декоративно-защитного покрытия на металлических основаниях. | I70: 0,9 л/2,7 л | J70: 10–14 м 2 /1 л | K70: Новинка | L70: https://osnovit.ru/catalog/emali/emal-po-metallu-univita-studio-metallo-eas821-pm20/
A71: Основит | B71: product | C71: Эмаль для окон и дверей Univita Studio Porta EAс831 ПМ20 | D71: Основит Univita Studio Porta EAс831 | E71: база А / база С; 0,9 л / 2,7 л | F71: paint | G71: no | H71: Эмаль ДЛЯ ОКОН И ДВЕРЕЙ: ОСНОВИТ UNIVITA Studio Porta EAс831 ПМ20 акриловая полуматовая предназначена для создания гладкого декоративно-защитного покрытия на оконных блоках, подоконниках, дверях, любых изделиях и конструкциях из дерева и дерево содержащих основаниях. | I71: 0,9 л/2,7 л | J71: 10–14 м 2 /1 л | K71: Новинка | L71: https://osnovit.ru/catalog/emali/emal-dlya-okon-i-dverey-univita-studio-porta-eas831-pm20/
A72: Основит | B72: product | C72: Краска интерьерная полуматовая Основит Univita Studio Prime I | D72: Основит Univita Studio Prime I | F72: paint | G72: no | H72: Предназначена для окрашивания стен и потолков в помещениях с нормальной и повышенной влажностью. | I72: 0,9 л/2,7 л/9 л | J72: 10–14 м 2 /1 л | K72: Колеровка | L72: https://osnovit.ru/catalog/kraski/interernaya-kraska-polumatovaya-moyushchayasya-dlya-sten-i-potolkov-osnovit-univita-studio-prime-i-s/
A73: Основит | B73: product | C73: Грунт интерьерный Основит Univita Studio Primer 10 л | D73: Основит Univita Studio Primer | E73: 10 л | F73: primer | G73: no | H73: Интерьерная грунтовка глубокого проникновения Основит Univita Studio PRIMER предназначена для грунтования минеральных поверхностей перед финишной окраской водно-дисперсионными красками в помещениях любого типа. | I73: 10 л | J73: 4–10 м 2 /л | L73: https://osnovit.ru/catalog/kraski/grunt-interernyy-osnovit-univita-studio-primer/
A74: Основит | B74: product | C74: Эмаль для радиаторов отопления Univita Studio Termo EAс841 ПМ20 | D74: Основит Univita Studio Termo EAс841 | E74: база А / база С; 0,9 л / 2,7 л | F74: paint | G74: no | H74: Эмаль ПО МЕТАЛЛУ: ОСНОВИТ UNIVITA Studio Termo EAс841 ПМ20 акриловая полуматовая предназначена для окрашивания радиаторов и систем отопления. | I74: 0,9 л/2,7 л | J74: 10–14 м 2 /1 л | K74: Новинка | L74: https://osnovit.ru/catalog/emali/emal-dlya-radiatorov-otopleniya-univita-studio-termo-eas841-pm20/
A75: Основит | B75: product | C75: Гидроизоляция эластичная готовая Основит Акваскрин HA64 | D75: Основит Акваскрин HA64 | F75: waterproofing_liquid | G75: no | H75: предназначена для создания гидроизоляционного барьера на горизонтальных и вертикальных поверхностях с периодическим увлажнением в помещениях с любым уровнем влажности под последующую укладку керамической и клинкерной плитки, керамогранита, натурального и искусственного камня. | I75: 4,5 кг, 15 кг | J75: 0,35-0,5 кг | L75: https://osnovit.ru/catalog/gidroizolyatsiya/gidroizolyatsiya-gotovaya-elastichnaya-osnovit-khardskrin-hac64-/
A76: Основит | B76: product | C76: Лента гидроизоляционная армированная сеткой в коробе Основит Акваскрин HB70 | D76: Основит Акваскрин HB70 | F76: other | G76: no | H76: Применяется для гидроизоляции внутренних и внешних углов, мест сопряжений «пол-стена», деформационных швов, выводов труб, сливных отверстий во влажных помещениях и сооружениях: санузлах, душевых, балконах, террасах, производственных помещениях и т.д. | K76: Новинка | L76: https://osnovit.ru/catalog/gidroizolyatsiya/gidroizolyatsionnaya-lenta-armirovannaya-setkoy-v-korobe-osnovit-akvaskrin-hb70-10-m/
A77: Основит | B77: product | C77: Гидропломба Основит Акваскрин HC61 500 г | D77: Основит Акваскрин HC61 | E77: 500 г | F77: hydroplug | G77: yes | H77: предназначена для остановки протечек воды через трещины, щели, отверстия, швы в бетонных конструкциях, кирпичной кладке, цементной штукатурке или стяжке. | I77: 500 г | L77: https://osnovit.ru/catalog/gidroizolyatsiya/akvaskrin-t-61/
A78: Основит | B78: product | C78: Гидроизоляция эластичная однокомпонентная Основит Акваскрин HC62 E1K 20 кг | D78: Основит Акваскрин HC62 E1K | E78: 20 кг | F78: waterproofing_dry | G78: yes | H78: предназначена для устройства эластичных гидроизоляционных покрытий на минеральных основаниях, подвергающихся в процессе эксплуатации незначительным деформациям. | I78: 20 кг | J78: 1,3-1,5 кг/м² | L78: https://osnovit.ru/catalog/gidroizolyatsiya/akvaskrin-hc62-e1k-gidroizolyatsiya-elastichnaya-odnokomponentnaya-osnovit-/
A79: Основит | B79: product | C79: Гидроизоляция жесткая Основит Акваскрин HC63 20 кг | D79: Основит Акваскрин HC63 | E79: 20 кг | F79: waterproofing_dry | G79: yes | H79: предназначена для гидроизоляции фундаментов зданий, фасадов, цоколей, подвалов, балконов, террас, стен и полов во влажных помещениях. | I79: 20 кг | J79: 4,5 кг/м² | L79: https://osnovit.ru/catalog/gidroizolyatsiya/akvaskrin-ns63-zhestkaya-gidroizolyatsiya-osnovit-/
A80: Основит | B80: product | C80: Гидроизоляция проникающая водоостанавливающая Основит Акваскрин HC65 20 кг | D80: Основит Акваскрин HC65 | E80: 20 кг | F80: waterproofing_dry | G80: yes | H80: предназначена для гидроизоляции бетонных конструкций изнутри: | I80: 20 кг | L80: https://osnovit.ru/catalog/gidroizolyatsiya/akvaskrin-hc65-vodoostonavlivayushchaya-gidroizolyatsiya-pronikayushchaya-osnovit/
A81: Основит | B81: product | C81: Состав гидроизоляционный шовный с проникающим эффектом Основит Акваскрин HC66 4 кг | D81: Основит Акваскрин HC66 | E81: 4 кг | F81: waterproofing_dry | G81: yes | H81: применяется для заделки стабилизированных стыков примыкания и швов в бетонных, железобетонных и каменных конструкциях при отсутствии постоянной активной | I81: Полиэтиленовые мешки 4кг и 8кг | L81: https://osnovit.ru/catalog/gidroizolyatsiya/akvaskrin-hc66-shovnyy-gidroizolyatsionnyy-sostav-s-pronikayushchim-effektom-osnovit/
A82: Основит | B82: product | C82: Клей плиточный Основит Базпликс AC10 [C0T] 25 кг | D82: Основит Базпликс AC10 | F82: tile_adhesive | G82: yes | H82: Плиточный клей Основит Базпликс AC10 предназначен для облицовки стен и пола керамической плиткой. | I82: 25 кг | J82: 1,3-1,5 кг/м 2 | L82: https://osnovit.ru/catalog/plitochnye-klei/bazpliks-as10-kley-standart-dlya-keramicheskoy-plitki-osnovit/
A83: Основит | B83: product | C83: Шпаклевка цементная фасадная универсальная белая Основит Базсилк PC30 MW 20 кг | D83: Основит Базсилк PC30 | E83: белая (MW) | F83: putty_cement | G83: yes | H83: Шпаклевка ОСНОВИТ БАЗСИЛК PC30 MW предназначена для выравнивания стен и потолков в сухих и влажных помещениях, фасадов, цоколей. | I83: 20 кг | J83: 1,2 кг/м² | L83: https://osnovit.ru/catalog/shpaklevki/bazsilk-t-30/
A84: Основит | B84: duplicate_of_other | C84: ШПАКЛЕВКА ЦЕМЕНТНАЯ ФАСАДНАЯ БЕЛАЯ УНИВЕРСАЛЬНАЯ ОСНОВИТ БАЗСИЛК PC30 MW (Н) ТОЛЩИНА СЛОЯ 1-10 ММ | D84: Основит Базсилк PC30 | E84: белая (MW), карточка «(Н)» | F84: putty_cement | G84: yes | H84: Шпаклевка ОСНОВИТ БАЗСИЛК PC30 MW предназначена для выравнивания стен и потолков в сухих и влажных помещениях, фасадов, цоколей. | I84: 20 кг | J84: 1 кг/м² | L84: https://osnovit.ru/catalog/shpaklevki-tsementnye/shpaklevka-tsementnaya-fasadnaya-universalnaya-belaya-osnovit-bazsilk-pc30-mw-n-tolshchina-sloya-1-1/
A85: Основит | B85: product | C85: Шпаклевка цементная фасадная универсальная серая Основит Базсилк PC30 MG 20 кг | D85: Основит Базсилк PC30 | E85: серая (MG) | F85: putty_cement | G85: yes | H85: предназначена для выравнивания стен и потолков в сухих и влажных помещениях, фасадов, цоколей. | I85: 20 кг | J85: 1,2 кг/м² | L85: https://osnovit.ru/catalog/shpaklevki/bazsilk-pc30-mg/
A86: Основит | B86: product | C86: Клей плиточный белый Основит Белпликс AC141 W [С1T] | D86: Основит Белпликс AC141 W | F86: tile_adhesive | G86: yes | H86: Белый плиточный клей Основит Белпликс AC141 W предназначен для облицовки стен и пола плитами из мрамора, цветной и прозрачной стеклянной плиткой, декоративной мозаикой, стекло-блоками, гранитом, натуральным и искусственным камнем. | I86: 5 кг, 25 кг | J86: 1,3-1,4 кг/м 2 | L86: https://osnovit.ru/catalog/plitochnye-klei/belpliks-ac141-w-s1t-h-kley-plitochnyy-belyy-dlya-keramicheskoy-mozaiki-keramicheskoy-keramogranit/
A87: Основит | B87: product | C87: Шпаклевка цементная финишная белая Основит Белсилк PC32 W | D87: Основит Белсилк PC32 W | F87: putty_cement | G87: yes | H87: предназначена для финишного выравнивания фасадов зданий, стен и потолков в сухих и влажных помещениях. | I87: 5, 20 кг | J87: 1,2 кг/м² | L87: https://osnovit.ru/catalog/shpaklevki/belsilk-t-32/
A88: Основит | B88: product | C88: Грунт бетоноконтакт Основит Беттоконт LP55 | D88: Основит Беттоконт LP55 | F88: primer | G88: no | H88: Грунт ОСНОВИТ БЕТТОКОНТ LP55 предназначен для предварительной обработки плотных, слабовпитывающих влагу гладких оснований. | I88: 20 кг | J88: 4–5 м 2 /кг | L88: https://osnovit.ru/catalog/gruntovki/bettokont-lp55/
A89: Основит | B89: product | C89: Грунт бетоноконтакт Основит Беттоконт LP551 20 кг | D89: Основит Беттоконт LP551 | E89: 20 кг | F89: primer | G89: no | H89: Грунт ОСНОВИТ БЕТТОКОНТ LP551 предназначен для предварительной обработки плотных, слабовпитывающих влагу гладких оснований. | I89: 20 кг | J89: 3–4 м 2 /кг | K89: Новинка | L89: https://osnovit.ru/catalog/gruntovki/grunt-betonokontakt-osnovit-bettokont-lp551/
A90: Основит | B90: product | C90: Раствор цветной для расшивки швов Основит Бриксэйв XC30 20 кг | D90: Основит Бриксэйв XC30 | F90: joint_pointing_brick | G90: yes | H90: Раствор для расшивки швов ОСНОВИТ БРИКСЭЙВ ХС30 предназначен для отделки швов: | I90: 20 кг | J90: 5,0 | K90: Колеровка | L90: https://osnovit.ru/catalog/rasshivki/brikseyv-xc30/
A91: Основит | B91: product | C91: Цветной кладочный раствор для облицовочного кирпича Основит Брикформ MC11 (25 кг) Н | D91: Основит Брикформ MC11 | E91: 25 кг | F91: masonry_colored | G91: yes | H91: Кладочный раствор ОСНОВИТ БРИКФОРМ МС11 предназначен для кладки стен из керамического, силикатного и клинкерного облицовочного кирпича с возможностью расшивки швов в момент укладки. | I91: Вес упаковки 25 кг | J91: Расход смеси на 1 м2 кладки (шов 10 мм, кладка в 1/2 кирпича) 50 кг | K91: Колеровка | L91: https://osnovit.ru/catalog/tsvetnye-kladochnye-rastvory/kladochnyy-rastvor-osnovit-brikform-ms11-N/
A92: Основит | B92: product | C92: Раствор кладочный цветной для облицовочного кирпича Основит Брикформ MC11 25 кг | D92: Основит Брикформ MC11 | E92: 34 цвета (колеровка) | F92: masonry_colored | G92: yes | H92: Кладочный раствор ОСНОВИТ БРИКФОРМ МС11 предназначен для кладки стен из керамического, силикатного и клинкерного облицовочного кирпича с возможностью расшивки швов в момент укладки. | I92: Вес упаковки 25 кг | J92: Расход смеси на 1 м2 кладки (шов 10 мм, кладка в 1/2 кирпича) 50 кг | K92: Колеровка | L92: https://osnovit.ru/catalog/kladochnye-rastvory/kladochnyy-rastvor-osnovit-brikform-ms11/
A93: Основит | B93: product | C93: Раствор кладочный зимний для облицовочного кирпича Основит Брикформ MC11 F 25 кг | D93: Основит Брикформ MC11 | E93: зима; 17 цветов | F93: masonry_colored | G93: yes | H93: Кладочный раствор ОСНОВИТ БРИКФОРМ МС11 F зимний предназначен для кладки стен из облицовочного кирпича с водопоглощением до 12% с возможностью расшивки швов в момент укладки при температуре окружающей среды и основания от -10 до + 10°С. | I93: Мешок 25кг | J93: Расход смеси, кг на 1м² кладки (ложковая кладка) 50 кг | K93: Зима, Новинка | L93: https://osnovit.ru/catalog/kladochnye-rastvory/kladochnyy-rastvor-osnovit-brikform-ms11-f-zimniy-belyy-010/
A94: Основит | B94: product | C94: Раствор кладочный для кирпича с очень высоким водопоглощением Основит Брикформ MC11/1 25 кг | D94: Основит Брикформ MC11/1 | E94: 25 кг | F94: masonry_colored | G94: yes | H94: Кладочный раствор ОСНОВИТ БРИКФОРМ МС11/1 предназначен для кладки стен и перегородок из облицовочного кирпича с водопоглощением более 12% с возможностью расшивки швов в момент укладки. | I94: Вес упаковки 25 кг | J94: Расход смеси на 1 м 2 кладки (шов 10 мм, кладка в 1/2 кирпича) 50 кг | K94: Колеровка | L94: https://osnovit.ru/catalog/tsvetnye-kladochnye-rastvory/kladochnyy-rastvor-osnovit-brikform-ms11-1-N/
A95: Основит | B95: product | C95: Раствор кладочный цветной для облицовочного кирпича с высоким водопоглощением Основит Брикформ MC11/1 25 кг | D95: Основит Брикформ MC11/1 | E95: 34 цвета (колеровка) | F95: masonry_colored | G95: yes | H95: Кладочный раствор ОСНОВИТ БРИКФОРМ МС11/1 предназначен для кладки стен и перегородок из облицовочного кирпича с водопоглощением более 12% с возможностью расшивки швов в момент укладки. | I95: Вес упаковки 25 кг | J95: Расход смеси на 1 м 2 кладки (шов 10 мм, кладка в 1/2 кирпича) 50 кг | K95: Колеровка | L95: https://osnovit.ru/catalog/kladochnye-rastvory/kladochnyy-rastvor-osnovit-brikform-ms11-1/
A96: Основит | B96: product | C96: Раствор кладочный зимний белый для облицовочного кирпича Основит Брикформ MC11/1 F 25 кг | D96: Основит Брикформ MC11/1 | E96: зима, белый | F96: masonry_colored | G96: yes | H96: предназначен для кладки стен и перегородок из облицовочного кирпича водопоглощением более 12% с возможностью расшивки швов в момент укладки при температуре окружающей среды и основания от -10 до + 10°С. | I96: Мешок 25кг | J96: 50 кг | K96: Зима | L96: https://osnovit.ru/catalog/kladochnye-rastvory/kladochnyy-rastvor-osnovit-brikform-ms11-1-f/
A97: Основит | B97: product | C97: Шпаклевка гипсовая универсальная белая Основит Версилк PG34 W 20 кг | D97: Основит Версилк PG34 W | F97: putty_gypsum | G97: yes | H97: Шпаклевка ОСНОВИТ ВЕРСИЛК PG34 W предназначена для заделки швов и стыков ГКЛ и ГВЛ, для выравнивания ГКЛ, ГВЛ, ПГП и СМЛ, а также для финишного выравнивания стен и потолков в сухих помещениях. | I97: 20 кг | J97: 0,8-0,9 кг/м² | L97: https://osnovit.ru/catalog/shpaklevki/shpaklevka-gipsovaya-vyravnivayushchaya-belaya-versilk-pg-34-w/
A98: Основит | B98: product | C98: Пол полимерный финишный Основит Гардлайн FE01 (комплект) | D98: Основит Гардлайн FE01 | E98: комплект | F98: polymer_coating | G98: no | H98: прочное декоративное покрытие, защищённое от появления пыли и трещин, а также стойкое к химическим и механическим воздействиям. | I98: Комплексное решение: грунт, покрытие, флоки, кисть, палочки для перемешивания, перчатки | J98: 1,25 кг* | K98: Новинка | L98: https://osnovit.ru/catalog/polimernye-pokrytiya/guardline/
A99: Основит | B99: product | C99: Штукатурка гипсовая универсальная белая Основит Гипсвэлл PG25 W 30 кг | D99: Основит Гипсвэлл PG25 | E99: белая (W) | F99: plaster_gypsum | G99: yes | H99: ОСНОВИТ ГИПСВЭЛЛ PG25 W — универсальная гипсовая штукатурка белого цвета для выравнивания стен и потолков внутри помещений с нормальной влажностью. | I99: 30 кг | J99: 8-9 кг/м² | L99: https://osnovit.ru/catalog/shtukaturki/shtukaturka-gipsovaya-universalnayabelaya-osnovit-gipsvell-pg-25-w/
A100: Основит | B100: product | C100: Штукатурка гипсовая универсальная серая Основит Гипсвэлл PG25 30 кг | D100: Основит Гипсвэлл PG25 | E100: серая | F100: plaster_gypsum | G100: yes | H100: ОСНОВИТ ГИПСВЭЛЛ PG25 — универсальная гипсовая штукатурка серого цвета для выравнивания стен и потолков внутри помещений с нормальной влажностью. | I100: 30 кг | J100: 8-9 кг/м² | L100: https://osnovit.ru/catalog/shtukaturki/osnovit-gipsvell-seraya-pg-25-shtukaturka-gipsovaya-universalnaya/
...

Sheet Как собрано
A1: Как собрано
A2: 09.10.2026 обойдены все страницы раздела /catalog/ трёх сайтов: td-perel.ru (249 страниц), dauer.ru (79, из них 25 старых адресов отдают 404), osnovit.ru (640; к нему добавлена карта сайта).
A3: Карточек товара: Perel 197, Dauer 45, Основит 247 (у Основита один товар лежит в нескольких разделах — склеено по canonical). Из них страниц-подборок без своего товара: Perel 7, Основит 13.
A4: Каждая карточка разобрана в запись: назначение, фасовка, расход, толщина, норматив, до 14 характеристик — ДОСЛОВНО. Все 13 465 цитат программно сверены с текстом карточки: несовпадений 0.
A5: «Товар» = продукт без цвета, фасовки и зимней модификации (Perel SL — один товар, 28 карточек: 14 цветов × 25/50 кг).
A6: Три карточки Основита (Флайвэлл PC24/1 ML, Стартвэлл PC21, PC21 M) не учтены: судя по разделу «Штукатурка», это старые названия серии «Техно».
A7: Цены: у Perel на сайте показаны, у Dauer и Основита нет. На наш сайт цены производителей не ставим.
A8: Внутренние противоречия у производителей (расход в тексте и в характеристиках разный, «мешки по 25 кг» на карточке 50 кг и т.п.) — в столбце «Примечание разбора» листа «Товары»; спорные цифры на сайт без уточнения не выводим.
A9: Не собраны: ссылки на техкарты Основита (на страницах названы, адреса не вытащились обходом) — добрать при сборке.
